adder.v
// Adder circuit
`define AND and
`define OR or
`define XOR xor
`define NOT not

module structuralFullAdder
(
    output sum,
    output carryout,
    input a,
    input b,
    input carryin

);
    wire xor0, and0, and1;
    // Single bit adder with carryin / carryout
    `XOR xor0gate(xor0,a,b);
    `AND and0gate(and0,a,b);
    `XOR sumgate(sum,xor0,carryin);
    `AND and1gate(and1,xor0,carryin);
    `OR orgate(carryout,and0,and1);
endmodule

module FullAdder4bit
(
  output[31:0] sum,  // 2's complement sum of a and b
  output carryout,  // Carry out of the summation of a and b
  output overflow,  // True if the calculation resulted in an overflow
  output zeros,
  input[31:0] a,     // First operand in 2's complement format
  input[31:0] b,      // Second operand in 2's complement format
  input carryin       //subtractor option
);
    // Your Code Here
    wire[31:0] carryout0;

    genvar i;
    generate
      structuralFullAdder _adder (sum[0], carryout0[0], a[0], b[0], carryin);
      for (i = 1; i < 32; i = i+1)
        begin:genblock
          structuralFullAdder _adder (sum[i],carryout0[i], a[i], b[i],carryout0[i-1]);
        end
    endgenerate
    assign carryout = carryout0[31];
    wire negand, posand, a3inv, b3inv, s3inv,one;
    //wire[31:0] sInv;
    `NOT a3inv(a3inv, a[31]);
    `NOT b3inv(b3inv, b[31]);
    `NOT s3inv(s3inv, sum[31]);
    `AND posand(posand, a3inv, b3inv, carryout0[30]);
    `AND negand(negand, a[31], b[31], s3inv);
    `OR overflowgate(overflow, posand, negand);
    `OR zeroGate(one, sum[0],sum[1],sum[2],sum[3],sum[4],sum[5],sum[6],sum[7],sum[8],sum[9],sum[10],sum[11],sum[12],sum[13],sum[14],sum[15],sum[16],sum[17],sum[18],sum[19],sum[20],sum[21],sum[22],sum[23],sum[24],sum[25],sum[26],sum[27],sum[28],sum[29],sum[30],sum[31]);
    `NOT one2zero(zeros,one);


endmodule

adder.t.v
// Adder testbench
`timescale 1 ns / 1 ps
`include "adder.v"

module testFullAdder();
    reg [31:0] a, b;
    reg carryin;
    wire [31:0] result;
    wire carryout, overflow;
    wire zero;

    FullAdder4bit fulladder (result, carryout, overflow, zero, a, b,carryin);

    initial begin
    $dumpfile("adder.vcd");
    $dumpvars;
carryin = 0;
$display("operandA operandB | result overflow carryout zero");
a = 32'b01111111111111111111111111111111; b = 32'b00000000000000000000000000000001; #1000
if((result !== 32'b10000000000000000000000000000000) || (overflow !== 1) || (carryout !== 0) || (zero !== 0)) begin
  $display("%b        %b      %b      %b |        10000000000000000000000000000000 1        0        0",result,overflow, carryout, zero);
end
a = 32'b00000000000000000000000000000101; b = 32'b00000000000000000000000000001010; #1000
if((result !== 32'b00000000000000000000000000001111) || (overflow !== 0) || (carryout !== 0) || (zero !== 0)) begin
  $display("%b        %b      %b      %b |        00000000000000000000000000001111 0        0        0",result,overflow, carryout, zero);
end
a = 32'b10000000000000000000000000000000; b = 32'b10000000000000000000000000000000; #1000
if((result !== 32'b00000000000000000000000000000000) || (overflow !== 1) || (carryout !== 1) || (zero !== 1)) begin
  $display("%b        %b      %b      %b |        00000000000000000000000000000000 1        1        1",result,overflow, carryout, zero);
end
a = 32'b10001000110010100110110000000000; b = 32'b00001011111010111100001000000000; #1000
if((result !== 32'b10010100101101100010111000000000) || (overflow !== 0) || (carryout !== 0) || (zero !== 0)) begin
  $display("%b        %b      %b      %b |        10010100101101100010111000000000 0        0        0",result,overflow, carryout, zero);
end
a = 32'b11111111111111000011100100000110; b = 32'b00000000000000000000000111010101; #1000
if((result !== 32'b11111111111111000011101011011011) || (overflow !== 0) || (carryout !== 0) || (zero !== 0)) begin
  $display("%b        %b      %b      %b |        11111111111111000011101011011011 0        0        0",result,overflow, carryout, zero);
end
a = 32'b00001011111010111100001000000000; b = 32'b10001000110010100110110000000000; #1000
if((result !== 32'b10010100101101100010111000000000) || (overflow !== 0) || (carryout !== 0) || (zero !== 0)) begin
  $display("%b        %b      %b      %b |        10010100101101100010111000000000 0        0        0",result,overflow, carryout, zero);
end
a = 32'b11111111101001101010100111011100; b = 32'b00000000000000000000001011101110; #1000
if((result !== 32'b11111111101001101010110011001010) || (overflow !== 0) || (carryout !== 0) || (zero !== 0)) begin
  $display("%b        %b      %b      %b |        11111111101001101010110011001010 0        0        0",result,overflow, carryout, zero);
end
a = 32'b10000000000000000000000000000000; b = 32'b11111111111111111111111111111111; #1000
if((result !== 32'b01111111111111111111111111111111) || (overflow !== 1) || (carryout !== 1) || (zero !== 0)) begin
  $display("%b        %b      %b      %b |        01111111111111111111111111111111 1        1        0",result,overflow, carryout, zero);
end
a = 32'b11111111111111111111110000011000; b = 32'b11111111111111111111110000011000; #1000
if((result !== 32'b11111111111111111111100000110000) || (overflow !== 0) || (carryout !== 1) || (zero !== 0)) begin
  $display("%b        %b      %b      %b |        11111111111111111111100000110000 0        1        0",result,overflow, carryout, zero);
end
a = 32'b00000000000000000000000000000000; b = 32'b00000000000000000000000000000000; #1000
if((result !== 32'b00000000000000000000000000000000) || (overflow !== 0) || (carryout !== 0) || (zero !== 1)) begin
  $display("%b        %b      %b      %b |        00000000000000000000000000000000 0        0        1",result,overflow, carryout, zero);
end
a = 32'b00000000000001100001101010000000; b = 32'b11111111111110011110010110000000; #1000 //WRONG!!!
if((result !== 32'b00000000000000000000000000000000) || (overflow !== 0) || (carryout !== 1) || (zero !== 1)) begin
  $display("%b        %b      %b      %b |        00000000000000000000000000000000 0        1        1",result,overflow, carryout, zero);
end

$finish();
end
endmodule

adder.vcd
$date
	Wed Oct  3 00:09:19 2018
$end
$version
	Icarus Verilog
$end
$timescale
	1ps
$end
$scope module testFullAdder $end
$var wire 1 ! zero $end
$var wire 32 " result [31:0] $end
$var wire 1 # overflow $end
$var wire 1 $ carryout $end
$var reg 32 % a [31:0] $end
$var reg 32 & b [31:0] $end
$var reg 1 ' carryin $end
$scope module fulladder $end
$var wire 32 ( a [31:0] $end
$var wire 1 ) a3inv $end
$var wire 32 * b [31:0] $end
$var wire 1 + b3inv $end
$var wire 1 ' carryin $end
$var wire 1 , negand $end
$var wire 1 - one $end
$var wire 1 # overflow $end
$var wire 1 . posand $end
$var wire 1 / s3inv $end
$var wire 1 ! zeros $end
$var wire 32 0 sum [31:0] $end
$var wire 32 1 carryout0 [31:0] $end
$var wire 1 $ carryout $end
$scope begin genblock[1] $end
$scope module _adder $end
$var wire 1 2 a $end
$var wire 1 3 and0 $end
$var wire 1 4 and1 $end
$var wire 1 5 b $end
$var wire 1 6 carryin $end
$var wire 1 7 carryout $end
$var wire 1 8 sum $end
$var wire 1 9 xor0 $end
$upscope $end
$upscope $end
$scope begin genblock[2] $end
$scope module _adder $end
$var wire 1 : a $end
$var wire 1 ; and0 $end
$var wire 1 < and1 $end
$var wire 1 = b $end
$var wire 1 > carryin $end
$var wire 1 ? carryout $end
$var wire 1 @ sum $end
$var wire 1 A xor0 $end
$upscope $end
$upscope $end
$scope begin genblock[3] $end
$scope module _adder $end
$var wire 1 B a $end
$var wire 1 C and0 $end
$var wire 1 D and1 $end
$var wire 1 E b $end
$var wire 1 F carryin $end
$var wire 1 G carryout $end
$var wire 1 H sum $end
$var wire 1 I xor0 $end
$upscope $end
$upscope $end
$scope begin genblock[4] $end
$scope module _adder $end
$var wire 1 J a $end
$var wire 1 K and0 $end
$var wire 1 L and1 $end
$var wire 1 M b $end
$var wire 1 N carryin $end
$var wire 1 O carryout $end
$var wire 1 P sum $end
$var wire 1 Q xor0 $end
$upscope $end
$upscope $end
$scope begin genblock[5] $end
$scope module _adder $end
$var wire 1 R a $end
$var wire 1 S and0 $end
$var wire 1 T and1 $end
$var wire 1 U b $end
$var wire 1 V carryin $end
$var wire 1 W carryout $end
$var wire 1 X sum $end
$var wire 1 Y xor0 $end
$upscope $end
$upscope $end
$scope begin genblock[6] $end
$scope module _adder $end
$var wire 1 Z a $end
$var wire 1 [ and0 $end
$var wire 1 \ and1 $end
$var wire 1 ] b $end
$var wire 1 ^ carryin $end
$var wire 1 _ carryout $end
$var wire 1 ` sum $end
$var wire 1 a xor0 $end
$upscope $end
$upscope $end
$scope begin genblock[7] $end
$scope module _adder $end
$var wire 1 b a $end
$var wire 1 c and0 $end
$var wire 1 d and1 $end
$var wire 1 e b $end
$var wire 1 f carryin $end
$var wire 1 g carryout $end
$var wire 1 h sum $end
$var wire 1 i xor0 $end
$upscope $end
$upscope $end
$scope begin genblock[8] $end
$scope module _adder $end
$var wire 1 j a $end
$var wire 1 k and0 $end
$var wire 1 l and1 $end
$var wire 1 m b $end
$var wire 1 n carryin $end
$var wire 1 o carryout $end
$var wire 1 p sum $end
$var wire 1 q xor0 $end
$upscope $end
$upscope $end
$scope begin genblock[9] $end
$scope module _adder $end
$var wire 1 r a $end
$var wire 1 s and0 $end
$var wire 1 t and1 $end
$var wire 1 u b $end
$var wire 1 v carryin $end
$var wire 1 w carryout $end
$var wire 1 x sum $end
$var wire 1 y xor0 $end
$upscope $end
$upscope $end
$scope begin genblock[10] $end
$scope module _adder $end
$var wire 1 z a $end
$var wire 1 { and0 $end
$var wire 1 | and1 $end
$var wire 1 } b $end
$var wire 1 ~ carryin $end
$var wire 1 !" carryout $end
$var wire 1 "" sum $end
$var wire 1 #" xor0 $end
$upscope $end
$upscope $end
$scope begin genblock[11] $end
$scope module _adder $end
$var wire 1 $" a $end
$var wire 1 %" and0 $end
$var wire 1 &" and1 $end
$var wire 1 '" b $end
$var wire 1 (" carryin $end
$var wire 1 )" carryout $end
$var wire 1 *" sum $end
$var wire 1 +" xor0 $end
$upscope $end
$upscope $end
$scope begin genblock[12] $end
$scope module _adder $end
$var wire 1 ," a $end
$var wire 1 -" and0 $end
$var wire 1 ." and1 $end
$var wire 1 /" b $end
$var wire 1 0" carryin $end
$var wire 1 1" carryout $end
$var wire 1 2" sum $end
$var wire 1 3" xor0 $end
$upscope $end
$upscope $end
$scope begin genblock[13] $end
$scope module _adder $end
$var wire 1 4" a $end
$var wire 1 5" and0 $end
$var wire 1 6" and1 $end
$var wire 1 7" b $end
$var wire 1 8" carryin $end
$var wire 1 9" carryout $end
$var wire 1 :" sum $end
$var wire 1 ;" xor0 $end
$upscope $end
$upscope $end
$scope begin genblock[14] $end
$scope module _adder $end
$var wire 1 <" a $end
$var wire 1 =" and0 $end
$var wire 1 >" and1 $end
$var wire 1 ?" b $end
$var wire 1 @" carryin $end
$var wire 1 A" carryout $end
$var wire 1 B" sum $end
$var wire 1 C" xor0 $end
$upscope $end
$upscope $end
$scope begin genblock[15] $end
$scope module _adder $end
$var wire 1 D" a $end
$var wire 1 E" and0 $end
$var wire 1 F" and1 $end
$var wire 1 G" b $end
$var wire 1 H" carryin $end
$var wire 1 I" carryout $end
$var wire 1 J" sum $end
$var wire 1 K" xor0 $end
$upscope $end
$upscope $end
$scope begin genblock[16] $end
$scope module _adder $end
$var wire 1 L" a $end
$var wire 1 M" and0 $end
$var wire 1 N" and1 $end
$var wire 1 O" b $end
$var wire 1 P" carryin $end
$var wire 1 Q" carryout $end
$var wire 1 R" sum $end
$var wire 1 S" xor0 $end
$upscope $end
$upscope $end
$scope begin genblock[17] $end
$scope module _adder $end
$var wire 1 T" a $end
$var wire 1 U" and0 $end
$var wire 1 V" and1 $end
$var wire 1 W" b $end
$var wire 1 X" carryin $end
$var wire 1 Y" carryout $end
$var wire 1 Z" sum $end
$var wire 1 [" xor0 $end
$upscope $end
$upscope $end
$scope begin genblock[18] $end
$scope module _adder $end
$var wire 1 \" a $end
$var wire 1 ]" and0 $end
$var wire 1 ^" and1 $end
$var wire 1 _" b $end
$var wire 1 `" carryin $end
$var wire 1 a" carryout $end
$var wire 1 b" sum $end
$var wire 1 c" xor0 $end
$upscope $end
$upscope $end
$scope begin genblock[19] $end
$scope module _adder $end
$var wire 1 d" a $end
$var wire 1 e" and0 $end
$var wire 1 f" and1 $end
$var wire 1 g" b $end
$var wire 1 h" carryin $end
$var wire 1 i" carryout $end
$var wire 1 j" sum $end
$var wire 1 k" xor0 $end
$upscope $end
$upscope $end
$scope begin genblock[20] $end
$scope module _adder $end
$var wire 1 l" a $end
$var wire 1 m" and0 $end
$var wire 1 n" and1 $end
$var wire 1 o" b $end
$var wire 1 p" carryin $end
$var wire 1 q" carryout $end
$var wire 1 r" sum $end
$var wire 1 s" xor0 $end
$upscope $end
$upscope $end
$scope begin genblock[21] $end
$scope module _adder $end
$var wire 1 t" a $end
$var wire 1 u" and0 $end
$var wire 1 v" and1 $end
$var wire 1 w" b $end
$var wire 1 x" carryin $end
$var wire 1 y" carryout $end
$var wire 1 z" sum $end
$var wire 1 {" xor0 $end
$upscope $end
$upscope $end
$scope begin genblock[22] $end
$scope module _adder $end
$var wire 1 |" a $end
$var wire 1 }" and0 $end
$var wire 1 ~" and1 $end
$var wire 1 !# b $end
$var wire 1 "# carryin $end
$var wire 1 ## carryout $end
$var wire 1 $# sum $end
$var wire 1 %# xor0 $end
$upscope $end
$upscope $end
$scope begin genblock[23] $end
$scope module _adder $end
$var wire 1 &# a $end
$var wire 1 '# and0 $end
$var wire 1 (# and1 $end
$var wire 1 )# b $end
$var wire 1 *# carryin $end
$var wire 1 +# carryout $end
$var wire 1 ,# sum $end
$var wire 1 -# xor0 $end
$upscope $end
$upscope $end
$scope begin genblock[24] $end
$scope module _adder $end
$var wire 1 .# a $end
$var wire 1 /# and0 $end
$var wire 1 0# and1 $end
$var wire 1 1# b $end
$var wire 1 2# carryin $end
$var wire 1 3# carryout $end
$var wire 1 4# sum $end
$var wire 1 5# xor0 $end
$upscope $end
$upscope $end
$scope begin genblock[25] $end
$scope module _adder $end
$var wire 1 6# a $end
$var wire 1 7# and0 $end
$var wire 1 8# and1 $end
$var wire 1 9# b $end
$var wire 1 :# carryin $end
$var wire 1 ;# carryout $end
$var wire 1 <# sum $end
$var wire 1 =# xor0 $end
$upscope $end
$upscope $end
$scope begin genblock[26] $end
$scope module _adder $end
$var wire 1 ># a $end
$var wire 1 ?# and0 $end
$var wire 1 @# and1 $end
$var wire 1 A# b $end
$var wire 1 B# carryin $end
$var wire 1 C# carryout $end
$var wire 1 D# sum $end
$var wire 1 E# xor0 $end
$upscope $end
$upscope $end
$scope begin genblock[27] $end
$scope module _adder $end
$var wire 1 F# a $end
$var wire 1 G# and0 $end
$var wire 1 H# and1 $end
$var wire 1 I# b $end
$var wire 1 J# carryin $end
$var wire 1 K# carryout $end
$var wire 1 L# sum $end
$var wire 1 M# xor0 $end
$upscope $end
$upscope $end
$scope begin genblock[28] $end
$scope module _adder $end
$var wire 1 N# a $end
$var wire 1 O# and0 $end
$var wire 1 P# and1 $end
$var wire 1 Q# b $end
$var wire 1 R# carryin $end
$var wire 1 S# carryout $end
$var wire 1 T# sum $end
$var wire 1 U# xor0 $end
$upscope $end
$upscope $end
$scope begin genblock[29] $end
$scope module _adder $end
$var wire 1 V# a $end
$var wire 1 W# and0 $end
$var wire 1 X# and1 $end
$var wire 1 Y# b $end
$var wire 1 Z# carryin $end
$var wire 1 [# carryout $end
$var wire 1 \# sum $end
$var wire 1 ]# xor0 $end
$upscope $end
$upscope $end
$scope begin genblock[30] $end
$scope module _adder $end
$var wire 1 ^# a $end
$var wire 1 _# and0 $end
$var wire 1 `# and1 $end
$var wire 1 a# b $end
$var wire 1 b# carryin $end
$var wire 1 c# carryout $end
$var wire 1 d# sum $end
$var wire 1 e# xor0 $end
$upscope $end
$upscope $end
$scope begin genblock[31] $end
$scope module _adder $end
$var wire 1 f# a $end
$var wire 1 g# and0 $end
$var wire 1 h# and1 $end
$var wire 1 i# b $end
$var wire 1 j# carryin $end
$var wire 1 k# carryout $end
$var wire 1 l# sum $end
$var wire 1 m# xor0 $end
$upscope $end
$upscope $end
$scope module _adder $end
$var wire 1 n# a $end
$var wire 1 o# and0 $end
$var wire 1 p# and1 $end
$var wire 1 q# b $end
$var wire 1 ' carryin $end
$var wire 1 r# carryout $end
$var wire 1 s# sum $end
$var wire 1 t# xor0 $end
$upscope $end
$upscope $end
$upscope $end
$enddefinitions $end
#0
$dumpvars
0t#
0s#
1r#
1q#
0p#
1o#
1n#
0m#
1l#
0k#
1j#
0i#
0h#
0g#
0f#
1e#
0d#
1c#
1b#
0a#
1`#
0_#
1^#
1]#
0\#
1[#
1Z#
0Y#
1X#
0W#
1V#
1U#
0T#
1S#
1R#
0Q#
1P#
0O#
1N#
1M#
0L#
1K#
1J#
0I#
1H#
0G#
1F#
1E#
0D#
1C#
1B#
0A#
1@#
0?#
1>#
1=#
0<#
1;#
1:#
09#
18#
07#
16#
15#
04#
13#
12#
01#
10#
0/#
1.#
1-#
0,#
1+#
1*#
0)#
1(#
0'#
1&#
1%#
0$#
1##
1"#
0!#
1~"
0}"
1|"
1{"
0z"
1y"
1x"
0w"
1v"
0u"
1t"
1s"
0r"
1q"
1p"
0o"
1n"
0m"
1l"
1k"
0j"
1i"
1h"
0g"
1f"
0e"
1d"
1c"
0b"
1a"
1`"
0_"
1^"
0]"
1\"
1["
0Z"
1Y"
1X"
0W"
1V"
0U"
1T"
1S"
0R"
1Q"
1P"
0O"
1N"
0M"
1L"
1K"
0J"
1I"
1H"
0G"
1F"
0E"
1D"
1C"
0B"
1A"
1@"
0?"
1>"
0="
1<"
1;"
0:"
19"
18"
07"
16"
05"
14"
13"
02"
11"
10"
0/"
1."
0-"
1,"
1+"
0*"
1)"
1("
0'"
1&"
0%"
1$"
1#"
0""
1!"
1~
0}
1|
0{
1z
1y
0x
1w
1v
0u
1t
0s
1r
1q
0p
1o
1n
0m
1l
0k
1j
1i
0h
1g
1f
0e
1d
0c
1b
1a
0`
1_
1^
0]
1\
0[
1Z
1Y
0X
1W
1V
0U
1T
0S
1R
1Q
0P
1O
1N
0M
1L
0K
1J
1I
0H
1G
1F
0E
1D
0C
1B
1A
0@
1?
1>
0=
1<
0;
1:
19
08
17
16
05
14
03
12
b1111111111111111111111111111111 1
b10000000000000000000000000000000 0
0/
1.
1-
0,
1+
b1 *
1)
b1111111111111111111111111111111 (
0'
b1 &
b1111111111111111111111111111111 %
0$
1#
b10000000000000000000000000000000 "
0!
$end
#1000000
0N
0G
1H
0D
0F
0?
1@
0<
1/
0>
0#
07
0.
0l#
18
04
0V
0^
0f
0n
0v
0~
0("
00"
08"
0@"
0H"
0P"
0X"
0`"
0h"
0p"
0x"
0"#
0*#
02#
0:#
0B#
0J#
0R#
0Z#
0b#
0j#
06
0O
0W
0_
0g
0o
0w
0!"
0)"
01"
09"
0A"
0I"
0Q"
0Y"
0a"
0i"
0q"
0y"
0##
0+#
03#
0;#
0C#
0K#
0S#
0[#
0c#
1s#
b0 1
0r#
0P
0L
0X
0T
0`
0\
0h
0d
0p
0l
0x
0t
0""
0|
0*"
0&"
02"
0."
0:"
06"
0B"
0>"
0J"
0F"
0R"
0N"
0Z"
0V"
0b"
0^"
0j"
0f"
0r"
0n"
0z"
0v"
0$#
0~"
0,#
0(#
04#
00#
0<#
08#
0D#
0@#
0L#
0H#
0T#
0P#
0\#
0X#
b1111 "
b1111 0
0d#
0`#
1t#
0o#
0Q
0Y
0a
0i
0q
0y
0#"
0+"
03"
0;"
0C"
0K"
0S"
0["
0c"
0k"
0s"
0{"
0%#
0-#
05#
0=#
0E#
0M#
0U#
0]#
0e#
15
1E
0q#
02
0B
0J
0R
0Z
0b
0j
0r
0z
0$"
0,"
04"
0<"
0D"
0L"
0T"
0\"
0d"
0l"
0t"
0|"
0&#
0.#
06#
0>#
0F#
0N#
0V#
0^#
b1010 &
b1010 *
b101 %
b101 (
#2000000
1!
0-
1$
08
0H
0@
b10000000000000000000000000000000 1
1k#
b0 "
b0 0
0s#
1#
09
0I
0+
0A
1g#
0t#
0)
1,
05
0E
1i#
0:
1f#
0n#
b10000000000000000000000000000000 &
b10000000000000000000000000000000 *
b10000000000000000000000000000000 %
b10000000000000000000000000000000 (
#3000000
1Z"
1D#
1X"
1B#
1Q"
1;#
0!
1N"
18#
1-
1P"
1:#
1I"
13#
0/
1F"
1b"
1r"
1,#
10#
1T#
0$
1H"
1`"
1p"
1*#
12#
1R#
1x
0J"
0R"
1z"
04#
0<#
1l#
0k#
0#
1""
1*"
b10010100101101100010111000000000 "
b10010100101101100010111000000000 0
1:"
1A"
1Y"
1i"
1##
1+#
b1011110010111100000000000000 1
1K#
1y
1K"
1S"
1{"
15#
1=#
1m#
0g#
1+
0,
1#"
1+"
1;"
1="
1U"
1e"
1}"
1'#
1G#
1u
1?"
1G"
1O"
1W"
1g"
1w"
1!#
1)#
11#
19#
1I#
0i#
1z
1$"
14"
1<"
1T"
1d"
1|"
1&#
1F#
b1011111010111100001000000000 &
b1011111010111100001000000000 *
b10001000110010100110110000000000 %
b10001000110010100110110000000000 (
#4000000
0/
0$
0k#
1l#
0h#
0j#
0B#
0c#
0;#
0~"
0`#
1<#
08#
0"#
0b#
0:#
0y"
0[#
0Z"
03#
0f"
1z"
0v"
0H#
0X#
0P"
0X"
14#
00#
1H
0h"
0x"
0J#
0Z#
0I"
0Q"
0p"
0*#
02#
0R#
1F
1v
0H"
0`"
0a"
0q"
0C#
0S#
1P
1`
1h
1x
0J"
0F"
0R"
0N"
1j"
0i"
1$#
0##
1,#
0(#
0+#
1L#
0K#
1s#
18
1?
1o
0""
12"
0A"
b100000100 1
0Y"
1b"
0^"
1r"
0n"
1D#
0@#
1T#
0P#
1\#
b11111111111111000011101011011011 "
b11111111111111000011101011011011 0
1d#
1Q
1a
1i
0y
0K"
0S"
1k"
0e"
1%#
0}"
1-#
0'#
1M#
0G#
1t#
19
1;
1k
0#"
13"
0="
0U"
1c"
1s"
1E#
1U#
1]#
1e#
1=
1M
1]
1e
1m
0u
0?"
0G"
0O"
0W"
0g"
0w"
0!#
0)#
01#
09#
0I#
1q#
12
1:
1j
0z
1,"
0<"
0T"
1\"
1l"
1t"
1.#
16#
1>#
1N#
1V#
1^#
b111010101 &
b111010101 *
b11111111111111000011100100000110 %
b11111111111111000011100100000110 (
#5000000
00"
1Z"
1B#
0)"
1X"
1;#
1*"
0&"
1Q"
0<#
18#
0("
1N"
1:#
0!"
1P"
13#
0|
1I"
04#
10#
0H
0~
1F"
1p"
1*#
12#
1R#
0F
0v
0w
1H"
1`"
0P
0`
0h
1""
0j"
1i"
0$#
1##
1,#
1+#
0L#
1K#
0s#
08
0?
0o
1x
0t
02"
1A"
0J"
0R"
b1011110010111100000000000000 1
1Y"
1b"
1r"
1D#
1T#
0\#
b10010100101101100010111000000000 "
b10010100101101100010111000000000 0
0d#
0Q
0a
0i
1#"
0k"
1e"
0%#
1}"
0-#
1'#
0M#
1G#
0t#
0+
09
0;
0k
1y
03"
1="
1K"
1S"
1U"
0c"
0s"
0E#
0U#
0]#
0e#
1)
0=
0M
0]
0e
0m
1}
1'"
17"
1?"
1W"
1g"
1!#
1)#
1I#
1i#
0q#
02
0:
0j
1r
0$"
0,"
04"
1<"
1D"
1L"
1T"
0\"
0l"
0>#
0N#
0V#
0^#
0f#
b10001000110010100110110000000000 &
b10001000110010100110110000000000 *
b1011111010111100001000000000 %
b1011111010111100001000000000 (
#6000000
0/
0$
0k#
1l#
0h#
1`
0j#
0B#
1^
1~
0c#
0;#
1W
1w
0`#
1<#
08#
1T
0x
1t
0b#
0:#
1V
1v
0P"
0[#
03#
1O
1o
0I"
0j"
0H#
0X#
14#
00#
1H
1L
1h
1l
1J"
0F"
0X"
0h"
0r"
0J#
0Z#
0`"
02#
0R#
1F
1N
1f
1n
0H"
0Q"
0a"
0p"
0*#
0C#
0S#
18
0X
1""
1Z"
0V"
0Y"
1,#
0(#
0+#
1L#
0K#
1?
1G
0P
1_
1g
0p
0A"
0R"
0N"
1b"
0^"
0i"
b1111111100 1
0##
1D#
0@#
1T#
0P#
1\#
b11111111101001101010110011001010 "
b11111111101001101010110011001010 0
1d#
19
1Y
0#"
1["
0U"
1-#
0'#
1M#
0G#
1+
1;
1C
1Q
1[
1c
1q
0="
0S"
1c"
0e"
0}"
1E#
1U#
1]#
1e#
0)
15
1=
1E
1U
1]
1e
1u
0}
0'"
07"
0?"
0W"
0g"
0!#
0)#
0I#
0i#
1:
1B
1J
1Z
1b
1j
0r
1$"
14"
0<"
0L"
1\"
0d"
0|"
1>#
1N#
1V#
1^#
1f#
b1011101110 &
b1011101110 *
b11111111101001101010100111011100 %
b11111111101001101010100111011100 (
#7000000
0j#
0c#
1d#
0`#
0b#
0[#
1\#
0X#
0Z#
0S#
1T#
0P#
0R#
0K#
1L#
0H#
0J#
0C#
1D#
0@#
0B#
0;#
1<#
08#
0:#
03#
14#
00#
02#
0+#
1,#
0(#
0*#
0##
0~"
0"#
0y"
1z"
0v"
0x"
0q"
0n"
0p"
0i"
0f"
0h"
0a"
1b"
0^"
0`"
0Y"
1Z"
0V"
0X"
0Q"
0N"
0P"
0I"
1J"
0F"
0H"
0A"
0>"
0@"
09"
1:"
06"
08"
01"
0^
0~
0."
0W
0w
00"
1X
0T
1x
0t
0)"
1#
0V
0v
1*"
0&"
1,
0O
0o
0("
1/
1P
0L
1p
0l
0!"
1$
0F
0N
0f
0n
1""
0|
12"
1B"
1R"
1j"
1r"
1$#
0l#
1k#
1s#
1@
0?
1H
0D
0G
1`
0\
0_
b1111111111111111111111111111111 "
b1111111111111111111111111111111 0
1h
0d
b10000000000000000000000000000000 1
0g
1#"
13"
1C"
1S"
1k"
1s"
1%#
0m#
1g#
1t#
0+
1A
0;
1I
0C
1a
0[
1i
0c
1M
1m
1}
1'"
1/"
17"
1?"
1G"
1O"
1W"
1_"
1g"
1o"
1w"
1!#
1)#
11#
19#
1A#
1I#
1Q#
1Y#
1a#
1i#
1q#
0:
0B
0J
0Z
0b
0j
0$"
04"
0D"
0T"
0\"
0t"
0&#
0.#
06#
0>#
0F#
0N#
0V#
0^#
b11111111111111111111111111111111 &
b11111111111111111111111111111111 *
b10000000000000000000000000000000 %
b10000000000000000000000000000000 (
#8000000
0#
0!
0,
1-
0/
1l#
1N
1V
1("
10"
18"
1@"
1H"
1P"
1X"
1`"
1h"
1p"
1x"
1"#
1*#
12#
1:#
1B#
1J#
1R#
1Z#
1b#
1j#
08
0@
1X
0`
0h
0p
0x
0s#
0H
1G
1P
1O
0""
1!"
1*"
1)"
12"
11"
1:"
19"
1B"
1A"
1J"
1I"
1R"
1Q"
1Z"
1Y"
1b"
1a"
1j"
1i"
1r"
1q"
1z"
1y"
1$#
1##
1,#
1+#
14#
13#
1<#
1;#
1D#
1C#
1L#
1K#
1T#
1S#
1\#
1[#
b11111111111111111111100000110000 "
b11111111111111111111100000110000 0
1d#
b11111111111111111111110000011000 1
1c#
09
0A
0Y
0a
0i
0q
0y
0t#
0I
1C
0Q
1K
0#"
1{
0+"
1%"
03"
1-"
0;"
15"
0C"
1="
0K"
1E"
0S"
1M"
0["
1U"
0c"
1]"
0k"
1e"
0s"
1m"
0{"
1u"
0%#
1}"
0-#
1'#
05#
1/#
0=#
17#
0E#
1?#
0M#
1G#
0U#
1O#
0]#
1W#
0e#
1_#
05
0=
0U
0]
0e
0m
0u
0q#
1B
1J
1z
1$"
1,"
14"
1<"
1D"
1L"
1T"
1\"
1d"
1l"
1t"
1|"
1&#
1.#
16#
1>#
1F#
1N#
1V#
1^#
b11111111111111111111110000011000 &
b11111111111111111111110000011000 *
b11111111111111111111110000011000 %
b11111111111111111111110000011000 (
#9000000
1!
0-
1/
0P
0X
0*"
02"
0:"
0B"
0J"
0R"
0Z"
0b"
0j"
0r"
0z"
0$#
0,#
04#
0<#
0D#
0L#
0T#
0\#
0d#
b0 "
b0 0
0l#
0N
0V
0("
00"
08"
0@"
0H"
0P"
0X"
0`"
0h"
0p"
0x"
0"#
0*#
02#
0:#
0B#
0J#
0R#
0Z#
0b#
0j#
0$
0#
0G
0O
0!"
0)"
01"
09"
0A"
0I"
0Q"
0Y"
0a"
0i"
0q"
0y"
0##
0+#
03#
0;#
0C#
0K#
0S#
0[#
0c#
b0 1
0k#
0.
1+
0C
0K
0{
0%"
0-"
05"
0="
0E"
0M"
0U"
0]"
0e"
0m"
0u"
0}"
0'#
0/#
07#
0?#
0G#
0O#
0W#
0_#
0g#
1)
0E
0M
0}
0'"
0/"
07"
0?"
0G"
0O"
0W"
0_"
0g"
0o"
0w"
0!#
0)#
01#
09#
0A#
0I#
0Q#
0Y#
0a#
0i#
0B
0J
0z
0$"
0,"
04"
0<"
0D"
0L"
0T"
0\"
0d"
0l"
0t"
0|"
0&#
0.#
06#
0>#
0F#
0N#
0V#
0^#
0f#
b0 &
b0 *
b0 %
b0 (
#10000000
1$
1k#
1h#
1j#
1c#
1`#
1b#
1[#
1X#
1Z#
1S#
1P#
1R#
1K#
1H#
1J#
1C#
1@#
1B#
1;#
18#
1:#
13#
10#
12#
1+#
1(#
1*#
1##
1~"
1"#
1y"
1v"
1x"
1q"
1n"
1p"
1i"
1f"
1h"
1a"
1^"
1`"
1Y"
1V"
1X"
1Q"
1N"
1P"
1I"
1F"
1H"
1A"
1>"
1@"
19"
16"
18"
11"
1."
10"
1)"
1&"
1("
1!"
1|
1~
1w
1t
1!
1v
0-
1o
1/
1l
1n
0p
0""
0:"
0B"
0J"
0R"
0j"
0r"
0z"
0$#
0,#
04#
0<#
0D#
0L#
0T#
0\#
0d#
0l#
b11111111111111111111111110000000 1
1g
0x
0*"
02"
0Z"
b0 "
b0 0
0b"
1q
1#"
1;"
1C"
1K"
1S"
1k"
1s"
1{"
1%#
1-#
15#
1=#
1E#
1M#
1U#
1]#
1e#
1m#
0+
1c
1y
1+"
13"
1["
1c"
1e
1m
1}
17"
1?"
1G"
1O"
1g"
1o"
1w"
1!#
1)#
11#
19#
1A#
1I#
1Q#
1Y#
1a#
1i#
1b
1r
1$"
1,"
1T"
1\"
b11111111111110011110010110000000 &
b11111111111110011110010110000000 *
b1100001101010000000 %
b1100001101010000000 (
