adder.v
// Adder circuit
`define AND2 and #30
`define OR2 or  #30
`define XOR2 xor  #30
`define NOT not #10
`define OR32 or #330
`define AND3 and  #40

module structuralFullAdder
(
    output sum,
    output carryout,
    input a,
    input b,
    input carryin

);
    wire xor0, and0, and1;
    // Single bit adder with carryin / carryout
    `XOR2 xor0gate(xor0,a,b);
    `AND2 and0gate(and0,a,b);
    `XOR2 sumgate(sum,xor0,carryin);
    `AND2 and1gate(and1,xor0,carryin);
    `OR2 orgate(carryout,and0,and1);
endmodule

module FullAdder32bit  //TODO: should change adder name to 32bit

(
  output[31:0] sum,  // 2's complement sum of a and b
  output carryout,  // Carry out of the summation of a and b
  output overflow,  // True if the calculation resulted in an overflow
  output zeros,
  input[31:0] a,     // First operand in 2's complement format
  input[31:0] b,      // Second operand in 2's complement format
  input carryin       //subtractor option
);
    // Your Code Here
    wire[31:0] carryout0;

    genvar i;
    generate
      structuralFullAdder _adder (sum[0], carryout0[0], a[0], b[0], carryin);
      for (i = 1; i < 32; i = i+1)
        begin:genblock
          structuralFullAdder _adder (sum[i],carryout0[i], a[i], b[i],carryout0[i-1]);
        end
    endgenerate
    assign carryout = carryout0[31];
    wire negand, posand, a3inv, b3inv, s3inv,one;
    //wire[31:0] sInv;
    `NOT a3inv(a3inv, a[31]);
    `NOT b3inv(b3inv, b[31]);
    `NOT s3inv(s3inv, sum[31]);
    `AND3 posand(posand, a3inv, b3inv, carryout0[30]);
    `AND3 negand(negand, a[31], b[31], s3inv);
    `OR2 overflowgate(overflow, posand, negand);
    `OR32 zeroGate(one, sum[0],sum[1],sum[2],sum[3],sum[4],sum[5],sum[6],sum[7],sum[8],sum[9],sum[10],sum[11],sum[12],sum[13],sum[14],sum[15],sum[16],sum[17],sum[18],sum[19],sum[20],sum[21],sum[22],sum[23],sum[24],sum[25],sum[26],sum[27],sum[28],sum[29],sum[30],sum[31]);
    `NOT one2zero(zeros,one);


endmodule

adder.t.v
// Adder testbench
`timescale 1 ns / 1 ps
`include "adder.v"

module testFullAdder();
    reg [31:0] a, b;
    reg carryin;
    wire [31:0] result;
    wire carryout, overflow;
    wire zero;

    FullAdder32bit adder32bit (result, carryout, overflow, zero, a, b,carryin);


    initial begin
    $dumpfile("adder.vcd");
    $dumpvars;
carryin = 0;
$display("operandA operandB | result overflow carryout zero");
a = 32'b01111111111111111111111111111111; b = 32'b00000000000000000000000000000001; #2500
if((result !== 32'b10000000000000000000000000000000) || (overflow !== 1) || (carryout !== 0) || (zero !== 0)) begin
  $display("%b        %b      %b      %b |        10000000000000000000000000000000 1        0        0",result,overflow, carryout, zero);
end
a = 32'b00000000000000000000000000000101; b = 32'b00000000000000000000000000001010; #2500
if((result !== 32'b00000000000000000000000000001111) || (overflow !== 0) || (carryout !== 0) || (zero !== 0)) begin
  $display("%b        %b      %b      %b |        00000000000000000000000000001111 0        0        0",result,overflow, carryout, zero);
end
a = 32'b10000000000000000000000000000000; b = 32'b10000000000000000000000000000000; #2500
if((result !== 32'b00000000000000000000000000000000) || (overflow !== 1) || (carryout !== 1) || (zero !== 1)) begin
  $display("%b        %b      %b      %b |        00000000000000000000000000000000 1        1        1",result,overflow, carryout, zero);
end
a = 32'b10001000110010100110110000000000; b = 32'b00001011111010111100001000000000; #2500
if((result !== 32'b10010100101101100010111000000000) || (overflow !== 0) || (carryout !== 0) || (zero !== 0)) begin
  $display("%b        %b      %b      %b |        10010100101101100010111000000000 0        0        0",result,overflow, carryout, zero);
end
a = 32'b11111111111111000011100100000110; b = 32'b00000000000000000000000111010101; #2500
if((result !== 32'b11111111111111000011101011011011) || (overflow !== 0) || (carryout !== 0) || (zero !== 0)) begin
  $display("%b        %b      %b      %b |        11111111111111000011101011011011 0        0        0",result,overflow, carryout, zero);
end
a = 32'b00001011111010111100001000000000; b = 32'b10001000110010100110110000000000; #2500
if((result !== 32'b10010100101101100010111000000000) || (overflow !== 0) || (carryout !== 0) || (zero !== 0)) begin
  $display("%b        %b      %b      %b |        10010100101101100010111000000000 0        0        0",result,overflow, carryout, zero);
end
a = 32'b11111111101001101010100111011100; b = 32'b00000000000000000000001011101110; #2500
if((result !== 32'b11111111101001101010110011001010) || (overflow !== 0) || (carryout !== 0) || (zero !== 0)) begin
  $display("%b        %b      %b      %b |        11111111101001101010110011001010 0        0        0",result,overflow, carryout, zero);
end
a = 32'b10000000000000000000000000000000; b = 32'b11111111111111111111111111111111; #2500
if((result !== 32'b01111111111111111111111111111111) || (overflow !== 1) || (carryout !== 1) || (zero !== 0)) begin
  $display("%b        %b      %b      %b |        01111111111111111111111111111111 1        1        0",result,overflow, carryout, zero);
end
a = 32'b11111111111111111111110000011000; b = 32'b11111111111111111111110000011000; #2500
if((result !== 32'b11111111111111111111100000110000) || (overflow !== 0) || (carryout !== 1) || (zero !== 0)) begin
  $display("%b        %b      %b      %b |        11111111111111111111100000110000 0        1        0",result,overflow, carryout, zero);
end
a = 32'b00000000000000000000000000000000; b = 32'b00000000000000000000000000000000; #2500
if((result !== 32'b00000000000000000000000000000000) || (overflow !== 0) || (carryout !== 0) || (zero !== 1)) begin
  $display("%b        %b      %b      %b |        00000000000000000000000000000000 0        0        1",result,overflow, carryout, zero);
end
a = 32'b00000000000001100001101010000000; b = 32'b11111111111110011110010110000000; #2500 //WRONG!!!
if((result !== 32'b00000000000000000000000000000000) || (overflow !== 0) || (carryout !== 1) || (zero !== 1)) begin
  $display("%b        %b      %b      %b |        00000000000000000000000000000000 0        1        1",result,overflow, carryout, zero);
end

$finish();
end
endmodule

adder.vcd
$date
	Thu Oct  4 14:19:43 2018
$end
$version
	Icarus Verilog
$end
$timescale
	1ps
$end
$scope module testFullAdder $end
$var wire 1 ! zero $end
$var wire 32 " result [31:0] $end
$var wire 1 # overflow $end
$var wire 1 $ carryout $end
$var reg 32 % a [31:0] $end
$var reg 32 & b [31:0] $end
$var reg 1 ' carryin $end
$scope module adder32bit $end
$var wire 32 ( a [31:0] $end
$var wire 1 ) a3inv $end
$var wire 32 * b [31:0] $end
$var wire 1 + b3inv $end
$var wire 1 ' carryin $end
$var wire 1 , negand $end
$var wire 1 - one $end
$var wire 1 # overflow $end
$var wire 1 . posand $end
$var wire 1 / s3inv $end
$var wire 1 ! zeros $end
$var wire 32 0 sum [31:0] $end
$var wire 32 1 carryout0 [31:0] $end
$var wire 1 $ carryout $end
$scope begin genblock[1] $end
$scope module _adder $end
$var wire 1 2 a $end
$var wire 1 3 and0 $end
$var wire 1 4 and1 $end
$var wire 1 5 b $end
$var wire 1 6 carryin $end
$var wire 1 7 carryout $end
$var wire 1 8 sum $end
$var wire 1 9 xor0 $end
$upscope $end
$upscope $end
$scope begin genblock[2] $end
$scope module _adder $end
$var wire 1 : a $end
$var wire 1 ; and0 $end
$var wire 1 < and1 $end
$var wire 1 = b $end
$var wire 1 > carryin $end
$var wire 1 ? carryout $end
$var wire 1 @ sum $end
$var wire 1 A xor0 $end
$upscope $end
$upscope $end
$scope begin genblock[3] $end
$scope module _adder $end
$var wire 1 B a $end
$var wire 1 C and0 $end
$var wire 1 D and1 $end
$var wire 1 E b $end
$var wire 1 F carryin $end
$var wire 1 G carryout $end
$var wire 1 H sum $end
$var wire 1 I xor0 $end
$upscope $end
$upscope $end
$scope begin genblock[4] $end
$scope module _adder $end
$var wire 1 J a $end
$var wire 1 K and0 $end
$var wire 1 L and1 $end
$var wire 1 M b $end
$var wire 1 N carryin $end
$var wire 1 O carryout $end
$var wire 1 P sum $end
$var wire 1 Q xor0 $end
$upscope $end
$upscope $end
$scope begin genblock[5] $end
$scope module _adder $end
$var wire 1 R a $end
$var wire 1 S and0 $end
$var wire 1 T and1 $end
$var wire 1 U b $end
$var wire 1 V carryin $end
$var wire 1 W carryout $end
$var wire 1 X sum $end
$var wire 1 Y xor0 $end
$upscope $end
$upscope $end
$scope begin genblock[6] $end
$scope module _adder $end
$var wire 1 Z a $end
$var wire 1 [ and0 $end
$var wire 1 \ and1 $end
$var wire 1 ] b $end
$var wire 1 ^ carryin $end
$var wire 1 _ carryout $end
$var wire 1 ` sum $end
$var wire 1 a xor0 $end
$upscope $end
$upscope $end
$scope begin genblock[7] $end
$scope module _adder $end
$var wire 1 b a $end
$var wire 1 c and0 $end
$var wire 1 d and1 $end
$var wire 1 e b $end
$var wire 1 f carryin $end
$var wire 1 g carryout $end
$var wire 1 h sum $end
$var wire 1 i xor0 $end
$upscope $end
$upscope $end
$scope begin genblock[8] $end
$scope module _adder $end
$var wire 1 j a $end
$var wire 1 k and0 $end
$var wire 1 l and1 $end
$var wire 1 m b $end
$var wire 1 n carryin $end
$var wire 1 o carryout $end
$var wire 1 p sum $end
$var wire 1 q xor0 $end
$upscope $end
$upscope $end
$scope begin genblock[9] $end
$scope module _adder $end
$var wire 1 r a $end
$var wire 1 s and0 $end
$var wire 1 t and1 $end
$var wire 1 u b $end
$var wire 1 v carryin $end
$var wire 1 w carryout $end
$var wire 1 x sum $end
$var wire 1 y xor0 $end
$upscope $end
$upscope $end
$scope begin genblock[10] $end
$scope module _adder $end
$var wire 1 z a $end
$var wire 1 { and0 $end
$var wire 1 | and1 $end
$var wire 1 } b $end
$var wire 1 ~ carryin $end
$var wire 1 !" carryout $end
$var wire 1 "" sum $end
$var wire 1 #" xor0 $end
$upscope $end
$upscope $end
$scope begin genblock[11] $end
$scope module _adder $end
$var wire 1 $" a $end
$var wire 1 %" and0 $end
$var wire 1 &" and1 $end
$var wire 1 '" b $end
$var wire 1 (" carryin $end
$var wire 1 )" carryout $end
$var wire 1 *" sum $end
$var wire 1 +" xor0 $end
$upscope $end
$upscope $end
$scope begin genblock[12] $end
$scope module _adder $end
$var wire 1 ," a $end
$var wire 1 -" and0 $end
$var wire 1 ." and1 $end
$var wire 1 /" b $end
$var wire 1 0" carryin $end
$var wire 1 1" carryout $end
$var wire 1 2" sum $end
$var wire 1 3" xor0 $end
$upscope $end
$upscope $end
$scope begin genblock[13] $end
$scope module _adder $end
$var wire 1 4" a $end
$var wire 1 5" and0 $end
$var wire 1 6" and1 $end
$var wire 1 7" b $end
$var wire 1 8" carryin $end
$var wire 1 9" carryout $end
$var wire 1 :" sum $end
$var wire 1 ;" xor0 $end
$upscope $end
$upscope $end
$scope begin genblock[14] $end
$scope module _adder $end
$var wire 1 <" a $end
$var wire 1 =" and0 $end
$var wire 1 >" and1 $end
$var wire 1 ?" b $end
$var wire 1 @" carryin $end
$var wire 1 A" carryout $end
$var wire 1 B" sum $end
$var wire 1 C" xor0 $end
$upscope $end
$upscope $end
$scope begin genblock[15] $end
$scope module _adder $end
$var wire 1 D" a $end
$var wire 1 E" and0 $end
$var wire 1 F" and1 $end
$var wire 1 G" b $end
$var wire 1 H" carryin $end
$var wire 1 I" carryout $end
$var wire 1 J" sum $end
$var wire 1 K" xor0 $end
$upscope $end
$upscope $end
$scope begin genblock[16] $end
$scope module _adder $end
$var wire 1 L" a $end
$var wire 1 M" and0 $end
$var wire 1 N" and1 $end
$var wire 1 O" b $end
$var wire 1 P" carryin $end
$var wire 1 Q" carryout $end
$var wire 1 R" sum $end
$var wire 1 S" xor0 $end
$upscope $end
$upscope $end
$scope begin genblock[17] $end
$scope module _adder $end
$var wire 1 T" a $end
$var wire 1 U" and0 $end
$var wire 1 V" and1 $end
$var wire 1 W" b $end
$var wire 1 X" carryin $end
$var wire 1 Y" carryout $end
$var wire 1 Z" sum $end
$var wire 1 [" xor0 $end
$upscope $end
$upscope $end
$scope begin genblock[18] $end
$scope module _adder $end
$var wire 1 \" a $end
$var wire 1 ]" and0 $end
$var wire 1 ^" and1 $end
$var wire 1 _" b $end
$var wire 1 `" carryin $end
$var wire 1 a" carryout $end
$var wire 1 b" sum $end
$var wire 1 c" xor0 $end
$upscope $end
$upscope $end
$scope begin genblock[19] $end
$scope module _adder $end
$var wire 1 d" a $end
$var wire 1 e" and0 $end
$var wire 1 f" and1 $end
$var wire 1 g" b $end
$var wire 1 h" carryin $end
$var wire 1 i" carryout $end
$var wire 1 j" sum $end
$var wire 1 k" xor0 $end
$upscope $end
$upscope $end
$scope begin genblock[20] $end
$scope module _adder $end
$var wire 1 l" a $end
$var wire 1 m" and0 $end
$var wire 1 n" and1 $end
$var wire 1 o" b $end
$var wire 1 p" carryin $end
$var wire 1 q" carryout $end
$var wire 1 r" sum $end
$var wire 1 s" xor0 $end
$upscope $end
$upscope $end
$scope begin genblock[21] $end
$scope module _adder $end
$var wire 1 t" a $end
$var wire 1 u" and0 $end
$var wire 1 v" and1 $end
$var wire 1 w" b $end
$var wire 1 x" carryin $end
$var wire 1 y" carryout $end
$var wire 1 z" sum $end
$var wire 1 {" xor0 $end
$upscope $end
$upscope $end
$scope begin genblock[22] $end
$scope module _adder $end
$var wire 1 |" a $end
$var wire 1 }" and0 $end
$var wire 1 ~" and1 $end
$var wire 1 !# b $end
$var wire 1 "# carryin $end
$var wire 1 ## carryout $end
$var wire 1 $# sum $end
$var wire 1 %# xor0 $end
$upscope $end
$upscope $end
$scope begin genblock[23] $end
$scope module _adder $end
$var wire 1 &# a $end
$var wire 1 '# and0 $end
$var wire 1 (# and1 $end
$var wire 1 )# b $end
$var wire 1 *# carryin $end
$var wire 1 +# carryout $end
$var wire 1 ,# sum $end
$var wire 1 -# xor0 $end
$upscope $end
$upscope $end
$scope begin genblock[24] $end
$scope module _adder $end
$var wire 1 .# a $end
$var wire 1 /# and0 $end
$var wire 1 0# and1 $end
$var wire 1 1# b $end
$var wire 1 2# carryin $end
$var wire 1 3# carryout $end
$var wire 1 4# sum $end
$var wire 1 5# xor0 $end
$upscope $end
$upscope $end
$scope begin genblock[25] $end
$scope module _adder $end
$var wire 1 6# a $end
$var wire 1 7# and0 $end
$var wire 1 8# and1 $end
$var wire 1 9# b $end
$var wire 1 :# carryin $end
$var wire 1 ;# carryout $end
$var wire 1 <# sum $end
$var wire 1 =# xor0 $end
$upscope $end
$upscope $end
$scope begin genblock[26] $end
$scope module _adder $end
$var wire 1 ># a $end
$var wire 1 ?# and0 $end
$var wire 1 @# and1 $end
$var wire 1 A# b $end
$var wire 1 B# carryin $end
$var wire 1 C# carryout $end
$var wire 1 D# sum $end
$var wire 1 E# xor0 $end
$upscope $end
$upscope $end
$scope begin genblock[27] $end
$scope module _adder $end
$var wire 1 F# a $end
$var wire 1 G# and0 $end
$var wire 1 H# and1 $end
$var wire 1 I# b $end
$var wire 1 J# carryin $end
$var wire 1 K# carryout $end
$var wire 1 L# sum $end
$var wire 1 M# xor0 $end
$upscope $end
$upscope $end
$scope begin genblock[28] $end
$scope module _adder $end
$var wire 1 N# a $end
$var wire 1 O# and0 $end
$var wire 1 P# and1 $end
$var wire 1 Q# b $end
$var wire 1 R# carryin $end
$var wire 1 S# carryout $end
$var wire 1 T# sum $end
$var wire 1 U# xor0 $end
$upscope $end
$upscope $end
$scope begin genblock[29] $end
$scope module _adder $end
$var wire 1 V# a $end
$var wire 1 W# and0 $end
$var wire 1 X# and1 $end
$var wire 1 Y# b $end
$var wire 1 Z# carryin $end
$var wire 1 [# carryout $end
$var wire 1 \# sum $end
$var wire 1 ]# xor0 $end
$upscope $end
$upscope $end
$scope begin genblock[30] $end
$scope module _adder $end
$var wire 1 ^# a $end
$var wire 1 _# and0 $end
$var wire 1 `# and1 $end
$var wire 1 a# b $end
$var wire 1 b# carryin $end
$var wire 1 c# carryout $end
$var wire 1 d# sum $end
$var wire 1 e# xor0 $end
$upscope $end
$upscope $end
$scope begin genblock[31] $end
$scope module _adder $end
$var wire 1 f# a $end
$var wire 1 g# and0 $end
$var wire 1 h# and1 $end
$var wire 1 i# b $end
$var wire 1 j# carryin $end
$var wire 1 k# carryout $end
$var wire 1 l# sum $end
$var wire 1 m# xor0 $end
$upscope $end
$upscope $end
$scope module _adder $end
$var wire 1 n# a $end
$var wire 1 o# and0 $end
$var wire 1 p# and1 $end
$var wire 1 q# b $end
$var wire 1 ' carryin $end
$var wire 1 r# carryout $end
$var wire 1 s# sum $end
$var wire 1 t# xor0 $end
$upscope $end
$upscope $end
$upscope $end
$enddefinitions $end
#0
$dumpvars
xt#
xs#
xr#
1q#
xp#
xo#
1n#
xm#
xl#
xk#
xj#
0i#
xh#
xg#
0f#
xe#
xd#
xc#
xb#
0a#
x`#
x_#
1^#
x]#
x\#
x[#
xZ#
0Y#
xX#
xW#
1V#
xU#
xT#
xS#
xR#
0Q#
xP#
xO#
1N#
xM#
xL#
xK#
xJ#
0I#
xH#
xG#
1F#
xE#
xD#
xC#
xB#
0A#
x@#
x?#
1>#
x=#
x<#
x;#
x:#
09#
x8#
x7#
16#
x5#
x4#
x3#
x2#
01#
x0#
x/#
1.#
x-#
x,#
x+#
x*#
0)#
x(#
x'#
1&#
x%#
x$#
x##
x"#
0!#
x~"
x}"
1|"
x{"
xz"
xy"
xx"
0w"
xv"
xu"
1t"
xs"
xr"
xq"
xp"
0o"
xn"
xm"
1l"
xk"
xj"
xi"
xh"
0g"
xf"
xe"
1d"
xc"
xb"
xa"
x`"
0_"
x^"
x]"
1\"
x["
xZ"
xY"
xX"
0W"
xV"
xU"
1T"
xS"
xR"
xQ"
xP"
0O"
xN"
xM"
1L"
xK"
xJ"
xI"
xH"
0G"
xF"
xE"
1D"
xC"
xB"
xA"
x@"
0?"
x>"
x="
1<"
x;"
x:"
x9"
x8"
07"
x6"
x5"
14"
x3"
x2"
x1"
x0"
0/"
x."
x-"
1,"
x+"
x*"
x)"
x("
0'"
x&"
x%"
1$"
x#"
x""
x!"
x~
0}
x|
x{
1z
xy
xx
xw
xv
0u
xt
xs
1r
xq
xp
xo
xn
0m
xl
xk
1j
xi
xh
xg
xf
0e
xd
xc
1b
xa
x`
x_
x^
0]
x\
x[
1Z
xY
xX
xW
xV
0U
xT
xS
1R
xQ
xP
xO
xN
0M
xL
xK
1J
xI
xH
xG
xF
0E
xD
xC
1B
xA
x@
x?
x>
0=
x<
x;
1:
x9
x8
x7
x6
05
x4
x3
12
bx 1
bx 0
x/
x.
x-
x,
x+
b1 *
x)
b1111111111111111111111111111111 (
0'
b1 &
b1111111111111111111111111111111 %
x$
x#
bx "
x!
$end
#10000
1+
1)
#30000
19
03
1A
0;
1I
0C
1Q
0K
1Y
0S
1a
0[
1i
0c
1q
0k
1y
0s
1#"
0{
1+"
0%"
13"
0-"
1;"
05"
1C"
0="
1K"
0E"
1S"
0M"
1["
0U"
1c"
0]"
1k"
0e"
1s"
0m"
1{"
0u"
1%#
0}"
1-#
0'#
15#
0/#
1=#
07#
1E#
0?#
1M#
0G#
1U#
0O#
1]#
0W#
1e#
0_#
0m#
0g#
0t#
1o#
0p#
#40000
0,
#60000
16
0h#
bx0 "
bx0 0
0s#
bx1 1
1r#
#90000
0$
bx00 "
bx00 0
08
14
b0xxxxxxxxxxxxxxxxxxxxxxxxxxxxxx1 1
0k#
#120000
1>
b0xxxxxxxxxxxxxxxxxxxxxxxxxxxxx11 1
17
#150000
bx000 "
bx000 0
0@
1<
#180000
1F
b0xxxxxxxxxxxxxxxxxxxxxxxxxxxx111 1
1?
#210000
bx0000 "
bx0000 0
0H
1D
#240000
1N
b0xxxxxxxxxxxxxxxxxxxxxxxxxxx1111 1
1G
#270000
bx00000 "
bx00000 0
0P
1L
#300000
1V
b0xxxxxxxxxxxxxxxxxxxxxxxxxx11111 1
1O
#330000
bx000000 "
bx000000 0
0X
1T
#360000
1^
b0xxxxxxxxxxxxxxxxxxxxxxxxx111111 1
1W
#390000
bx0000000 "
bx0000000 0
0`
1\
#420000
1f
b0xxxxxxxxxxxxxxxxxxxxxxxx1111111 1
1_
#450000
bx00000000 "
bx00000000 0
0h
1d
#480000
1n
b0xxxxxxxxxxxxxxxxxxxxxxx11111111 1
1g
#510000
bx000000000 "
bx000000000 0
0p
1l
#540000
1v
b0xxxxxxxxxxxxxxxxxxxxxx111111111 1
1o
#570000
bx0000000000 "
bx0000000000 0
0x
1t
#600000
1~
b0xxxxxxxxxxxxxxxxxxxxx1111111111 1
1w
#630000
bx00000000000 "
bx00000000000 0
0""
1|
#660000
1("
b0xxxxxxxxxxxxxxxxxxxx11111111111 1
1!"
#690000
bx000000000000 "
bx000000000000 0
0*"
1&"
#720000
10"
b0xxxxxxxxxxxxxxxxxxx111111111111 1
1)"
#750000
bx0000000000000 "
bx0000000000000 0
02"
1."
#780000
18"
b0xxxxxxxxxxxxxxxxxx1111111111111 1
11"
#810000
bx00000000000000 "
bx00000000000000 0
0:"
16"
#840000
1@"
b0xxxxxxxxxxxxxxxxx11111111111111 1
19"
#870000
bx000000000000000 "
bx000000000000000 0
0B"
1>"
#900000
1H"
b0xxxxxxxxxxxxxxxx111111111111111 1
1A"
#930000
bx0000000000000000 "
bx0000000000000000 0
0J"
1F"
#960000
1P"
b0xxxxxxxxxxxxxxx1111111111111111 1
1I"
#990000
bx00000000000000000 "
bx00000000000000000 0
0R"
1N"
#1020000
1X"
b0xxxxxxxxxxxxxx11111111111111111 1
1Q"
#1050000
bx000000000000000000 "
bx000000000000000000 0
0Z"
1V"
#1080000
1`"
b0xxxxxxxxxxxxx111111111111111111 1
1Y"
#1110000
bx0000000000000000000 "
bx0000000000000000000 0
0b"
1^"
#1140000
1h"
b0xxxxxxxxxxxx1111111111111111111 1
1a"
#1170000
bx00000000000000000000 "
bx00000000000000000000 0
0j"
1f"
#1200000
1p"
b0xxxxxxxxxxx11111111111111111111 1
1i"
#1230000
bx000000000000000000000 "
bx000000000000000000000 0
0r"
1n"
#1260000
1x"
b0xxxxxxxxxx111111111111111111111 1
1q"
#1290000
bx0000000000000000000000 "
bx0000000000000000000000 0
0z"
1v"
#1320000
1"#
b0xxxxxxxxx1111111111111111111111 1
1y"
#1350000
bx00000000000000000000000 "
bx00000000000000000000000 0
0$#
1~"
#1380000
1*#
b0xxxxxxxx11111111111111111111111 1
1##
#1410000
bx000000000000000000000000 "
bx000000000000000000000000 0
0,#
1(#
#1440000
12#
b0xxxxxxx111111111111111111111111 1
1+#
#1470000
bx0000000000000000000000000 "
bx0000000000000000000000000 0
04#
10#
#1500000
1:#
b0xxxxxx1111111111111111111111111 1
13#
#1530000
bx00000000000000000000000000 "
bx00000000000000000000000000 0
0<#
18#
#1560000
1B#
b0xxxxx11111111111111111111111111 1
1;#
#1590000
bx000000000000000000000000000 "
bx000000000000000000000000000 0
0D#
1@#
#1620000
1J#
b0xxxx111111111111111111111111111 1
1C#
#1650000
bx0000000000000000000000000000 "
bx0000000000000000000000000000 0
0L#
1H#
#1680000
1R#
b0xxx1111111111111111111111111111 1
1K#
#1710000
bx00000000000000000000000000000 "
bx00000000000000000000000000000 0
0T#
1P#
#1740000
1Z#
b0xx11111111111111111111111111111 1
1S#
#1770000
bx000000000000000000000000000000 "
bx000000000000000000000000000000 0
0\#
1X#
#1800000
1b#
b0x111111111111111111111111111111 1
1[#
#1830000
bx0000000000000000000000000000000 "
bx0000000000000000000000000000000 0
0d#
1`#
#1860000
1j#
b1111111111111111111111111111111 1
1c#
#1890000
b10000000000000000000000000000000 "
b10000000000000000000000000000000 0
1l#
#1900000
0/
1.
#1930000
1#
#2220000
1-
#2230000
0!
#2500000
15
1E
0q#
02
0B
0J
0R
0Z
0b
0j
0r
0z
0$"
0,"
04"
0<"
0D"
0L"
0T"
0\"
0d"
0l"
0t"
0|"
0&#
0.#
06#
0>#
0F#
0N#
0V#
0^#
b1010 &
b1010 *
b101 %
b101 (
#2530000
1t#
0o#
0Q
0Y
0a
0i
0q
0y
0#"
0+"
03"
0;"
0C"
0K"
0S"
0["
0c"
0k"
0s"
0{"
0%#
0-#
05#
0=#
0E#
0M#
0U#
0]#
0e#
#2560000
06
1s#
b1111111111111111111111111111110 1
0r#
1P
0L
1X
0T
1`
0\
1h
0d
1p
0l
1x
0t
1""
0|
1*"
0&"
12"
0."
1:"
06"
1B"
0>"
1J"
0F"
1R"
0N"
1Z"
0V"
1b"
0^"
1j"
0f"
1r"
0n"
1z"
0v"
1$#
0~"
1,#
0(#
14#
00#
1<#
08#
1D#
0@#
1L#
0H#
1T#
0P#
1\#
0X#
b11111111111111111111111111110001 "
b11111111111111111111111111110001 0
1d#
0`#
#2590000
0V
0^
0f
0n
0v
0~
0("
00"
08"
0@"
0H"
0P"
0X"
0`"
0h"
0p"
0x"
0"#
0*#
02#
0:#
0B#
0J#
0R#
0Z#
0b#
0j#
b11111111111111111111111111110011 "
b11111111111111111111111111110011 0
18
04
0O
0W
0_
0g
0o
0w
0!"
0)"
01"
09"
0A"
0I"
0Q"
0Y"
0a"
0i"
0q"
0y"
0##
0+#
03#
0;#
0C#
0K#
0S#
0[#
b1110 1
0c#
#2620000
0>
0X
0`
0h
0p
0x
0""
0*"
02"
0:"
0B"
0J"
0R"
0Z"
0b"
0j"
0r"
0z"
0$#
0,#
04#
0<#
0D#
0L#
0T#
0\#
0d#
b10011 "
b10011 0
0l#
b1100 1
07
#2630000
1/
0.
#2650000
b10111 "
b10111 0
1@
0<
#2660000
0#
#2680000
0F
b1000 1
0?
#2710000
b11111 "
b11111 0
1H
0D
#2740000
0N
b0 1
0G
#2770000
b1111 "
b1111 0
0P
#5000000
05
0E
1i#
0:
1f#
0n#
b10000000000000000000000000000000 &
b10000000000000000000000000000000 *
b10000000000000000000000000000000 %
b10000000000000000000000000000000 (
#5010000
0+
0)
#5030000
09
0I
0A
1g#
0t#
#5040000
1,
#5060000
1$
08
0H
0@
b10000000000000000000000000000000 1
1k#
b0 "
b0 0
0s#
#5070000
1#
#5390000
0-
#5400000
1!
#7500000
1u
1?"
1G"
1O"
1W"
1g"
1w"
1!#
1)#
11#
19#
1I#
0i#
1z
1$"
14"
1<"
1T"
1d"
1|"
1&#
1F#
b1011111010111100001000000000 &
b1011111010111100001000000000 *
b10001000110010100110110000000000 %
b10001000110010100110110000000000 (
#7510000
1+
#7530000
1y
1K"
1S"
1{"
15#
1=#
1m#
0g#
1#"
1+"
1;"
1="
1U"
1e"
1}"
1'#
1G#
#7540000
0,
#7560000
0$
1H"
1`"
1p"
1*#
12#
1R#
1x
1J"
1R"
1z"
14#
1<#
1l#
0k#
1""
1*"
b10000011001000011010111000000000 "
b10000011001000011010111000000000 0
1:"
1A"
1Y"
1i"
1##
1+#
b1000110010100100000000000000 1
1K#
#7570000
0/
0#
#7590000
0J"
1F"
1b"
1r"
1,#
04#
10#
b10010010101101010010111000000000 "
b10010010101101010010111000000000 0
1T#
#7620000
1P"
1:#
1I"
b1001110010101100000000000000 1
13#
#7650000
0R"
1N"
b10010000101101000010111000000000 "
b10010000101101000010111000000000 0
0<#
18#
#7680000
1X"
1B#
1Q"
b1011110010111100000000000000 1
1;#
#7710000
1Z"
b10010100101101100010111000000000 "
b10010100101101100010111000000000 0
1D#
#7890000
1-
#7900000
0!
#10000000
1=
1M
1]
1e
1m
0u
0?"
0G"
0O"
0W"
0g"
0w"
0!#
0)#
01#
09#
0I#
1q#
12
1:
1j
0z
1,"
0<"
0T"
1\"
1l"
1t"
1.#
16#
1>#
1N#
1V#
1^#
b111010101 &
b111010101 *
b11111111111111000011100100000110 %
b11111111111111000011100100000110 (
#10030000
1Q
1a
1i
0y
0K"
0S"
1k"
0e"
1%#
0}"
1-#
0'#
1M#
0G#
1t#
19
1;
1k
0#"
13"
0="
0U"
1c"
1s"
1E#
1U#
1]#
1e#
#10060000
0p"
0*#
02#
0R#
1F
1v
0H"
0`"
1P
1`
1h
0x
1J"
0F"
1R"
0N"
1j"
0i"
1$#
0##
0,#
1(#
0+#
1L#
0K#
1s#
18
1?
1o
0""
12"
0A"
b11000000011000000100000100 1
0Y"
0b"
1^"
0r"
1n"
0D#
1@#
0T#
1P#
1\#
b11101000011010111011100011010011 "
b11101000011010111011100011010011 0
1d#
#10090000
0P"
0X"
12#
1h"
1x"
1J#
1Z#
1r"
0n"
1,#
0(#
14#
00#
1T#
0P#
1H
1x
0J"
b11111001111111110011101011011011 "
b11111001111111110011101011011011 0
1b"
0^"
0I"
0Q"
1+#
1a"
1q"
1C#
b10111100101000000000100000100 1
1S#
#10120000
0x"
02#
0:#
0Z#
0h"
0R"
0Z"
04#
10#
0j"
1f"
0z"
1v"
0L#
1H#
b11010000110101000011101011011011 "
b11010000110101000011101011011011 0
0\#
1X#
0q"
0+#
03#
0S#
b110000000000000000100000100 1
0a"
#10150000
1:#
1p"
1"#
1R#
1b#
1z"
0v"
14#
00#
1<#
08#
1\#
0X#
b11110011111111000011101011011011 "
b11110011111111000011101011011011 0
1j"
0f"
13#
1i"
1y"
1K#
b101111001010000000000100000100 1
1[#
#10180000
0"#
0:#
0B#
0b#
0p"
0<#
18#
0r"
1n"
0$#
1~"
0T#
1P#
b10100001101011000011101011011011 "
b10100001101011000011101011011011 0
0d#
1`#
0y"
03#
0;#
0[#
b1100000000000000000100000100 1
0i"
#10210000
1B#
1x"
1*#
1Z#
1j#
1$#
0~"
1<#
08#
1D#
0@#
1d#
0`#
b11100111111111000011101011011011 "
b11100111111111000011101011011011 0
1r"
0n"
1;#
1q"
1##
1S#
b1011110010100000000000100000100 1
1c#
#10240000
0*#
0B#
0J#
0j#
0x"
0D#
1@#
0z"
1v"
0,#
1(#
0\#
1X#
b1000011010111000011101011011011 "
b1000011010111000011101011011011 0
0l#
1h#
0##
0;#
0C#
0c#
b11000000000000000000100000100 1
0q"
#10250000
1/
#10270000
1J#
1"#
12#
1b#
1$
1,#
0(#
1D#
0@#
1L#
0H#
1l#
0h#
b11001111111111000011101011011011 "
b11001111111111000011101011011011 0
1z"
0v"
1C#
1y"
1+#
1[#
b10111100101000000000000100000100 1
1k#
#10280000
0/
