adder.v
// Adder circuit
`define AND and #50
`define OR or #50
`define XOR xor #50
`define NOT not #50

module structuralFullAdder
(
    output sum,
    output carryout,
    input a,
    input b,
    input carryin

);
    wire xor0, and0, and1;
    // Single bit adder with carryin / carryout
    `XOR xor0gate(xor0,a,b);
    `AND and0gate(and0,a,b);
    `XOR sumgate(sum,xor0,carryin);
    `AND and1gate(and1,xor0,carryin);
    `OR orgate(carryout,and0,and1);
endmodule

module FullAdder4bit
(
  output[31:0] sum,  // 2's complement sum of a and b
  output carryout,  // Carry out of the summation of a and b
  output overflow,  // True if the calculation resulted in an overflow
  input[31:0] a,     // First operand in 2's complement format
  input[31:0] b,      // Second operand in 2's complement format
  input carryin       //subtractor option
);
    // Your Code Here
    wire[31:0] carryout0;

    genvar i;
    generate
      structuralFullAdder _adder (sum[0], carryout0[0], a[0], b[0], carryin);
      for (i = 1; i < 32; i = i+1)
        begin:genblock
          structuralFullAdder _adder (sum[i],carryout0[i], a[i], b[i],carryout0[i-1]);
        end
    endgenerate
    assign carryout = carryout0[31];
    wire negand, posand, a3inv, b3inv, s3inv;
    `NOT a3inv(a3inv, a[31]);
    `NOT b3inv(b3inv, b[31]);
    `NOT s3inv(s3inv, sum[31]);
    `AND posand(posand, a3inv, b3inv, carryout0[31]);
    `AND negand(negand, a[31], b[31], s3inv);
    `OR overflowgate(overflow, posand, negand);

endmodule

adder.t.v
// Adder testbench
`timescale 1 ns / 1 ps
`include "adder.v"

module testFullAdder();
    reg [31:0] a, b;
    reg carryin;
    wire [31:0] result;
    wire carryout, overflow;
    reg zero;

    FullAdder4bit fulladder (result, carryout, overflow, a, b,carryin);

    initial begin
    $dumpfile("adder.vcd");
    $dumpvars;
carryin = 0;
zero = 0;
$display("operandA operandB | result overflow carryout zero");
a = 32'b01111111111111111111111111111111; b = 32'b00000000000000000000000000000001; #1000
if((result !== 32'b10000000000000000000000000000000) || (overflow !== 1) || (carryout !== 0) || (zero !== 0)) begin
  $display("%b        %b      %b |        10000000000000000000000000000000 1        0        0",result,overflow, carryout);
end
a = 32'b00000000000000000000000000000101; b = 32'b00000000000000000000000000001010; #1000
if((result !== 32'b00000000000000000000000000001111) || (overflow !== 0) || (carryout !== 0) || (zero !== 0)) begin
  $display("%b        %b      %b |        00000000000000000000000000001111 0        0        0",result,overflow, carryout);
end
a = 32'b10000000000000000000000000000000; b = 32'b10000000000000000000000000000000; #1000
if((result !== 32'b00000000000000000000000000000000) || (overflow !== 1) || (carryout !== 1) || (zero !== 1)) begin
  $display("%b        %b      %b |        00000000000000000000000000000000 1        1        1",result,overflow, carryout);
end
a = 32'b10001000110010100110110000000000; b = 32'b00001011111010111100001000000000; #1000
if((result !== 32'b10010100101101100010111000000000) || (overflow !== 0) || (carryout !== 0) || (zero !== 0)) begin
  $display("%b        %b      %b |        10010100101101100010111000000000 0        0        0",result,overflow, carryout);
end
a = 32'b11111111111111000011100100000110; b = 32'b00000000000000000000000111010101; #1000
if((result !== 32'b11111111111111000011101011011011) || (overflow !== 0) || (carryout !== 0) || (zero !== 0)) begin
  $display("%b        %b      %b |        11111111111111000011101011011011 0        0        0",result,overflow, carryout);
end
a = 32'b00001011111010111100001000000000; b = 32'b10001000110010100110110000000000; #1000
if((result !== 32'b10010100101101100010111000000000) || (overflow !== 0) || (carryout !== 0) || (zero !== 0)) begin
  $display("%b        %b      %b |        10010100101101100010111000000000 0        0        0",result,overflow, carryout);
end
a = 32'b11111111101001101010100111011100; b = 32'b00000000000000000000001011101110; #1000
if((result !== 32'b11111111101001101010110011001010) || (overflow !== 0) || (carryout !== 0) || (zero !== 0)) begin
  $display("%b        %b      %b |        11111111101001101010110011001010 0        0        0",result,overflow, carryout);
end
a = 32'b10000000000000000000000000000000; b = 32'b11111111111111111111111111111111; #1000
if((result !== 32'b01111111111111111111111111111111) || (overflow !== 1) || (carryout !== 1) || (zero !== 0)) begin
  $display("%b        %b      %b |        01111111111111111111111111111111 1        1        0",result,overflow, carryout);
end
a = 32'b11111111111111111111110000011000; b = 32'b11111111111111111111110000011000; #1000
if((result !== 32'b11111111111111111111100000110000) || (overflow !== 0) || (carryout !== 1) || (zero !== 0)) begin
  $display("%b        %b      %b |        11111111111111111111100000110000 0        1        0",result,overflow, carryout);
end
a = 32'b00000000000000000000000000000000; b = 32'b00000000000000000000000000000000; #1000
if((result !== 32'b00000000000000000000000000000000) || (overflow !== 0) || (carryout !== 0) || (zero !== 1)) begin
  $display("%b        %b      %b |        00000000000000000000000000000000 0        0        1",result,overflow, carryout);
end
a = 32'b00000000000001100001101010000000; b = 32'b11111111111110011110010110000000; #1000 //WRONG!!!
if((result !== 32'b00000000000000000000000000000000) || (overflow !== 0) || (carryout !== 0) || (zero !== 1)) begin
  $display("%b        %b      %b |        00000000000000000000000000000000 0        0        1",result,overflow, carryout);
end

$finish();
end
endmodule

adder.vcd
$date
	Tue Oct  2 18:11:57 2018
$end
$version
	Icarus Verilog
$end
$timescale
	1ps
$end
$scope module testFullAdder $end
$var wire 32 ! result [31:0] $end
$var wire 1 " overflow $end
$var wire 1 # carryout $end
$var reg 32 $ a [31:0] $end
$var reg 32 % b [31:0] $end
$var reg 1 & carryin $end
$var reg 1 ' zero $end
$scope module fulladder $end
$var wire 32 ( a [31:0] $end
$var wire 1 ) a3inv $end
$var wire 32 * b [31:0] $end
$var wire 1 + b3inv $end
$var wire 1 & carryin $end
$var wire 1 , negand $end
$var wire 1 " overflow $end
$var wire 1 - posand $end
$var wire 1 . s3inv $end
$var wire 32 / sum [31:0] $end
$var wire 32 0 carryout0 [31:0] $end
$var wire 1 # carryout $end
$scope begin genblock[1] $end
$scope module _adder $end
$var wire 1 1 a $end
$var wire 1 2 and0 $end
$var wire 1 3 and1 $end
$var wire 1 4 b $end
$var wire 1 5 carryin $end
$var wire 1 6 carryout $end
$var wire 1 7 sum $end
$var wire 1 8 xor0 $end
$upscope $end
$upscope $end
$scope begin genblock[2] $end
$scope module _adder $end
$var wire 1 9 a $end
$var wire 1 : and0 $end
$var wire 1 ; and1 $end
$var wire 1 < b $end
$var wire 1 = carryin $end
$var wire 1 > carryout $end
$var wire 1 ? sum $end
$var wire 1 @ xor0 $end
$upscope $end
$upscope $end
$scope begin genblock[3] $end
$scope module _adder $end
$var wire 1 A a $end
$var wire 1 B and0 $end
$var wire 1 C and1 $end
$var wire 1 D b $end
$var wire 1 E carryin $end
$var wire 1 F carryout $end
$var wire 1 G sum $end
$var wire 1 H xor0 $end
$upscope $end
$upscope $end
$scope begin genblock[4] $end
$scope module _adder $end
$var wire 1 I a $end
$var wire 1 J and0 $end
$var wire 1 K and1 $end
$var wire 1 L b $end
$var wire 1 M carryin $end
$var wire 1 N carryout $end
$var wire 1 O sum $end
$var wire 1 P xor0 $end
$upscope $end
$upscope $end
$scope begin genblock[5] $end
$scope module _adder $end
$var wire 1 Q a $end
$var wire 1 R and0 $end
$var wire 1 S and1 $end
$var wire 1 T b $end
$var wire 1 U carryin $end
$var wire 1 V carryout $end
$var wire 1 W sum $end
$var wire 1 X xor0 $end
$upscope $end
$upscope $end
$scope begin genblock[6] $end
$scope module _adder $end
$var wire 1 Y a $end
$var wire 1 Z and0 $end
$var wire 1 [ and1 $end
$var wire 1 \ b $end
$var wire 1 ] carryin $end
$var wire 1 ^ carryout $end
$var wire 1 _ sum $end
$var wire 1 ` xor0 $end
$upscope $end
$upscope $end
$scope begin genblock[7] $end
$scope module _adder $end
$var wire 1 a a $end
$var wire 1 b and0 $end
$var wire 1 c and1 $end
$var wire 1 d b $end
$var wire 1 e carryin $end
$var wire 1 f carryout $end
$var wire 1 g sum $end
$var wire 1 h xor0 $end
$upscope $end
$upscope $end
$scope begin genblock[8] $end
$scope module _adder $end
$var wire 1 i a $end
$var wire 1 j and0 $end
$var wire 1 k and1 $end
$var wire 1 l b $end
$var wire 1 m carryin $end
$var wire 1 n carryout $end
$var wire 1 o sum $end
$var wire 1 p xor0 $end
$upscope $end
$upscope $end
$scope begin genblock[9] $end
$scope module _adder $end
$var wire 1 q a $end
$var wire 1 r and0 $end
$var wire 1 s and1 $end
$var wire 1 t b $end
$var wire 1 u carryin $end
$var wire 1 v carryout $end
$var wire 1 w sum $end
$var wire 1 x xor0 $end
$upscope $end
$upscope $end
$scope begin genblock[10] $end
$scope module _adder $end
$var wire 1 y a $end
$var wire 1 z and0 $end
$var wire 1 { and1 $end
$var wire 1 | b $end
$var wire 1 } carryin $end
$var wire 1 ~ carryout $end
$var wire 1 !" sum $end
$var wire 1 "" xor0 $end
$upscope $end
$upscope $end
$scope begin genblock[11] $end
$scope module _adder $end
$var wire 1 #" a $end
$var wire 1 $" and0 $end
$var wire 1 %" and1 $end
$var wire 1 &" b $end
$var wire 1 '" carryin $end
$var wire 1 (" carryout $end
$var wire 1 )" sum $end
$var wire 1 *" xor0 $end
$upscope $end
$upscope $end
$scope begin genblock[12] $end
$scope module _adder $end
$var wire 1 +" a $end
$var wire 1 ," and0 $end
$var wire 1 -" and1 $end
$var wire 1 ." b $end
$var wire 1 /" carryin $end
$var wire 1 0" carryout $end
$var wire 1 1" sum $end
$var wire 1 2" xor0 $end
$upscope $end
$upscope $end
$scope begin genblock[13] $end
$scope module _adder $end
$var wire 1 3" a $end
$var wire 1 4" and0 $end
$var wire 1 5" and1 $end
$var wire 1 6" b $end
$var wire 1 7" carryin $end
$var wire 1 8" carryout $end
$var wire 1 9" sum $end
$var wire 1 :" xor0 $end
$upscope $end
$upscope $end
$scope begin genblock[14] $end
$scope module _adder $end
$var wire 1 ;" a $end
$var wire 1 <" and0 $end
$var wire 1 =" and1 $end
$var wire 1 >" b $end
$var wire 1 ?" carryin $end
$var wire 1 @" carryout $end
$var wire 1 A" sum $end
$var wire 1 B" xor0 $end
$upscope $end
$upscope $end
$scope begin genblock[15] $end
$scope module _adder $end
$var wire 1 C" a $end
$var wire 1 D" and0 $end
$var wire 1 E" and1 $end
$var wire 1 F" b $end
$var wire 1 G" carryin $end
$var wire 1 H" carryout $end
$var wire 1 I" sum $end
$var wire 1 J" xor0 $end
$upscope $end
$upscope $end
$scope begin genblock[16] $end
$scope module _adder $end
$var wire 1 K" a $end
$var wire 1 L" and0 $end
$var wire 1 M" and1 $end
$var wire 1 N" b $end
$var wire 1 O" carryin $end
$var wire 1 P" carryout $end
$var wire 1 Q" sum $end
$var wire 1 R" xor0 $end
$upscope $end
$upscope $end
$scope begin genblock[17] $end
$scope module _adder $end
$var wire 1 S" a $end
$var wire 1 T" and0 $end
$var wire 1 U" and1 $end
$var wire 1 V" b $end
$var wire 1 W" carryin $end
$var wire 1 X" carryout $end
$var wire 1 Y" sum $end
$var wire 1 Z" xor0 $end
$upscope $end
$upscope $end
$scope begin genblock[18] $end
$scope module _adder $end
$var wire 1 [" a $end
$var wire 1 \" and0 $end
$var wire 1 ]" and1 $end
$var wire 1 ^" b $end
$var wire 1 _" carryin $end
$var wire 1 `" carryout $end
$var wire 1 a" sum $end
$var wire 1 b" xor0 $end
$upscope $end
$upscope $end
$scope begin genblock[19] $end
$scope module _adder $end
$var wire 1 c" a $end
$var wire 1 d" and0 $end
$var wire 1 e" and1 $end
$var wire 1 f" b $end
$var wire 1 g" carryin $end
$var wire 1 h" carryout $end
$var wire 1 i" sum $end
$var wire 1 j" xor0 $end
$upscope $end
$upscope $end
$scope begin genblock[20] $end
$scope module _adder $end
$var wire 1 k" a $end
$var wire 1 l" and0 $end
$var wire 1 m" and1 $end
$var wire 1 n" b $end
$var wire 1 o" carryin $end
$var wire 1 p" carryout $end
$var wire 1 q" sum $end
$var wire 1 r" xor0 $end
$upscope $end
$upscope $end
$scope begin genblock[21] $end
$scope module _adder $end
$var wire 1 s" a $end
$var wire 1 t" and0 $end
$var wire 1 u" and1 $end
$var wire 1 v" b $end
$var wire 1 w" carryin $end
$var wire 1 x" carryout $end
$var wire 1 y" sum $end
$var wire 1 z" xor0 $end
$upscope $end
$upscope $end
$scope begin genblock[22] $end
$scope module _adder $end
$var wire 1 {" a $end
$var wire 1 |" and0 $end
$var wire 1 }" and1 $end
$var wire 1 ~" b $end
$var wire 1 !# carryin $end
$var wire 1 "# carryout $end
$var wire 1 ## sum $end
$var wire 1 $# xor0 $end
$upscope $end
$upscope $end
$scope begin genblock[23] $end
$scope module _adder $end
$var wire 1 %# a $end
$var wire 1 &# and0 $end
$var wire 1 '# and1 $end
$var wire 1 (# b $end
$var wire 1 )# carryin $end
$var wire 1 *# carryout $end
$var wire 1 +# sum $end
$var wire 1 ,# xor0 $end
$upscope $end
$upscope $end
$scope begin genblock[24] $end
$scope module _adder $end
$var wire 1 -# a $end
$var wire 1 .# and0 $end
$var wire 1 /# and1 $end
$var wire 1 0# b $end
$var wire 1 1# carryin $end
$var wire 1 2# carryout $end
$var wire 1 3# sum $end
$var wire 1 4# xor0 $end
$upscope $end
$upscope $end
$scope begin genblock[25] $end
$scope module _adder $end
$var wire 1 5# a $end
$var wire 1 6# and0 $end
$var wire 1 7# and1 $end
$var wire 1 8# b $end
$var wire 1 9# carryin $end
$var wire 1 :# carryout $end
$var wire 1 ;# sum $end
$var wire 1 <# xor0 $end
$upscope $end
$upscope $end
$scope begin genblock[26] $end
$scope module _adder $end
$var wire 1 =# a $end
$var wire 1 ># and0 $end
$var wire 1 ?# and1 $end
$var wire 1 @# b $end
$var wire 1 A# carryin $end
$var wire 1 B# carryout $end
$var wire 1 C# sum $end
$var wire 1 D# xor0 $end
$upscope $end
$upscope $end
$scope begin genblock[27] $end
$scope module _adder $end
$var wire 1 E# a $end
$var wire 1 F# and0 $end
$var wire 1 G# and1 $end
$var wire 1 H# b $end
$var wire 1 I# carryin $end
$var wire 1 J# carryout $end
$var wire 1 K# sum $end
$var wire 1 L# xor0 $end
$upscope $end
$upscope $end
$scope begin genblock[28] $end
$scope module _adder $end
$var wire 1 M# a $end
$var wire 1 N# and0 $end
$var wire 1 O# and1 $end
$var wire 1 P# b $end
$var wire 1 Q# carryin $end
$var wire 1 R# carryout $end
$var wire 1 S# sum $end
$var wire 1 T# xor0 $end
$upscope $end
$upscope $end
$scope begin genblock[29] $end
$scope module _adder $end
$var wire 1 U# a $end
$var wire 1 V# and0 $end
$var wire 1 W# and1 $end
$var wire 1 X# b $end
$var wire 1 Y# carryin $end
$var wire 1 Z# carryout $end
$var wire 1 [# sum $end
$var wire 1 \# xor0 $end
$upscope $end
$upscope $end
$scope begin genblock[30] $end
$scope module _adder $end
$var wire 1 ]# a $end
$var wire 1 ^# and0 $end
$var wire 1 _# and1 $end
$var wire 1 `# b $end
$var wire 1 a# carryin $end
$var wire 1 b# carryout $end
$var wire 1 c# sum $end
$var wire 1 d# xor0 $end
$upscope $end
$upscope $end
$scope begin genblock[31] $end
$scope module _adder $end
$var wire 1 e# a $end
$var wire 1 f# and0 $end
$var wire 1 g# and1 $end
$var wire 1 h# b $end
$var wire 1 i# carryin $end
$var wire 1 j# carryout $end
$var wire 1 k# sum $end
$var wire 1 l# xor0 $end
$upscope $end
$upscope $end
$scope module _adder $end
$var wire 1 m# a $end
$var wire 1 n# and0 $end
$var wire 1 o# and1 $end
$var wire 1 p# b $end
$var wire 1 & carryin $end
$var wire 1 q# carryout $end
$var wire 1 r# sum $end
$var wire 1 s# xor0 $end
$upscope $end
$upscope $end
$upscope $end
$enddefinitions $end
#0
$dumpvars
xs#
xr#
xq#
1p#
xo#
xn#
1m#
xl#
xk#
xj#
xi#
0h#
xg#
xf#
0e#
xd#
xc#
xb#
xa#
0`#
x_#
x^#
1]#
x\#
x[#
xZ#
xY#
0X#
xW#
xV#
1U#
xT#
xS#
xR#
xQ#
0P#
xO#
xN#
1M#
xL#
xK#
xJ#
xI#
0H#
xG#
xF#
1E#
xD#
xC#
xB#
xA#
0@#
x?#
x>#
1=#
x<#
x;#
x:#
x9#
08#
x7#
x6#
15#
x4#
x3#
x2#
x1#
00#
x/#
x.#
1-#
x,#
x+#
x*#
x)#
0(#
x'#
x&#
1%#
x$#
x##
x"#
x!#
0~"
x}"
x|"
1{"
xz"
xy"
xx"
xw"
0v"
xu"
xt"
1s"
xr"
xq"
xp"
xo"
0n"
xm"
xl"
1k"
xj"
xi"
xh"
xg"
0f"
xe"
xd"
1c"
xb"
xa"
x`"
x_"
0^"
x]"
x\"
1["
xZ"
xY"
xX"
xW"
0V"
xU"
xT"
1S"
xR"
xQ"
xP"
xO"
0N"
xM"
xL"
1K"
xJ"
xI"
xH"
xG"
0F"
xE"
xD"
1C"
xB"
xA"
x@"
x?"
0>"
x="
x<"
1;"
x:"
x9"
x8"
x7"
06"
x5"
x4"
13"
x2"
x1"
x0"
x/"
0."
x-"
x,"
1+"
x*"
x)"
x("
x'"
0&"
x%"
x$"
1#"
x""
x!"
x~
x}
0|
x{
xz
1y
xx
xw
xv
xu
0t
xs
xr
1q
xp
xo
xn
xm
0l
xk
xj
1i
xh
xg
xf
xe
0d
xc
xb
1a
x`
x_
x^
x]
0\
x[
xZ
1Y
xX
xW
xV
xU
0T
xS
xR
1Q
xP
xO
xN
xM
0L
xK
xJ
1I
xH
xG
xF
xE
0D
xC
xB
1A
x@
x?
x>
x=
0<
x;
x:
19
x8
x7
x6
x5
04
x3
x2
11
bx 0
bx /
x.
x-
x,
x+
b1 *
x)
b1111111111111111111111111111111 (
0'
0&
b1 %
b1111111111111111111111111111111 $
x#
x"
bx !
$end
#50000
1+
18
02
1@
0:
1H
0B
1P
0J
1X
0R
1`
0Z
1h
0b
1p
0j
1x
0r
1""
0z
1*"
0$"
12"
0,"
1:"
04"
1B"
0<"
1J"
0D"
1R"
0L"
1Z"
0T"
1b"
0\"
1j"
0d"
1r"
0l"
1z"
0t"
1$#
0|"
1,#
0&#
14#
0.#
1<#
06#
1D#
0>#
1L#
0F#
1T#
0N#
1\#
0V#
1d#
0^#
0l#
0f#
0s#
1n#
1)
0,
0o#
#100000
15
0g#
bx0 !
bx0 /
0r#
bx1 0
1q#
#150000
0#
bx00 !
bx00 /
07
13
b0xxxxxxxxxxxxxxxxxxxxxxxxxxxxxx1 0
0j#
#200000
1=
0-
b0xxxxxxxxxxxxxxxxxxxxxxxxxxxxx11 0
16
#250000
bx000 !
bx000 /
0?
1;
0"
#300000
1E
b0xxxxxxxxxxxxxxxxxxxxxxxxxxxx111 0
1>
#350000
bx0000 !
bx0000 /
0G
1C
#400000
1M
b0xxxxxxxxxxxxxxxxxxxxxxxxxxx1111 0
1F
#450000
bx00000 !
bx00000 /
0O
1K
#500000
1U
b0xxxxxxxxxxxxxxxxxxxxxxxxxx11111 0
1N
#550000
bx000000 !
bx000000 /
0W
1S
#600000
1]
b0xxxxxxxxxxxxxxxxxxxxxxxxx111111 0
1V
#650000
bx0000000 !
bx0000000 /
0_
1[
#700000
1e
b0xxxxxxxxxxxxxxxxxxxxxxxx1111111 0
1^
#750000
bx00000000 !
bx00000000 /
0g
1c
#800000
1m
b0xxxxxxxxxxxxxxxxxxxxxxx11111111 0
1f
#850000
bx000000000 !
bx000000000 /
0o
1k
#900000
1u
b0xxxxxxxxxxxxxxxxxxxxxx111111111 0
1n
#950000
bx0000000000 !
bx0000000000 /
0w
1s
#1000000
1}
14
1D
0p#
01
0A
0I
0Q
0Y
0a
0i
0q
0y
0#"
0+"
03"
0;"
0C"
0K"
0S"
0["
0c"
0k"
0s"
0{"
0%#
0-#
05#
0=#
0E#
0M#
0U#
0]#
b0xxxxxxxxxxxxxxxxxxxxx1111111111 0
1v
b1010 %
b1010 *
b101 $
b101 (
#1050000
bx00000000000 !
bx00000000000 /
0!"
1{
1s#
0n#
0P
0X
0`
0h
0p
0x
0""
0*"
02"
0:"
0B"
0J"
0R"
0Z"
0b"
0j"
0r"
0z"
0$#
0,#
04#
0<#
0D#
0L#
0T#
0\#
0d#
#1100000
1'"
05
1~
1r#
b0xxxxxxxxxxxxxxxxxxxx11111111110 0
0q#
1O
0K
1W
0S
1_
0[
1g
0c
1o
0k
1w
0s
bx11111110001 !
bx11111110001 /
1!"
0{
0%"
0-"
05"
0="
0E"
0M"
0U"
0]"
0e"
0m"
0u"
0}"
0'#
0/#
07#
0?#
0G#
0O#
0W#
0_#
#1150000
0U
0]
0e
0m
0u
0}
0'"
0/"
07"
0?"
0G"
0O"
0W"
0_"
0g"
0o"
0w"
0!#
0)#
01#
09#
0A#
0I#
0Q#
0Y#
0a#
0i#
1)"
bx111111110011 !
bx111111110011 /
17
03
0N
0V
0^
0f
0n
0v
0~
0("
00"
08"
0@"
0H"
0P"
0X"
0`"
0h"
0p"
0x"
0"#
0*#
02#
0:#
0B#
0J#
0R#
0Z#
b1110 0
0b#
#1200000
0=
0W
0_
0g
0o
0w
0!"
0)"
01"
09"
0A"
0I"
0Q"
0Y"
0a"
0i"
0q"
0y"
0##
0+#
03#
0;#
0C#
0K#
0S#
0[#
0c#
b10011 !
b10011 /
0k#
b1100 0
06
#1250000
1.
b10111 !
b10111 /
1?
0;
#1300000
0E
b1000 0
0>
#1350000
b11111 !
b11111 /
1G
0C
#1400000
0M
b0 0
0F
#1450000
b1111 !
b1111 /
0O
#2000000
04
0D
1h#
09
1e#
0m#
b10000000000000000000000000000000 %
b10000000000000000000000000000000 *
b10000000000000000000000000000000 $
b10000000000000000000000000000000 (
#2050000
08
0H
0+
0@
1f#
0s#
0)
1,
#2100000
1#
07
0G
0?
b10000000000000000000000000000000 0
1j#
b0 !
b0 /
0r#
1"
#3000000
1t
1>"
1F"
1N"
1V"
1f"
1v"
1~"
1(#
10#
18#
1H#
0h#
1y
1#"
13"
1;"
1S"
1c"
1{"
1%#
1E#
b1011111010111100001000000000 %
b1011111010111100001000000000 *
b10001000110010100110110000000000 $
b10001000110010100110110000000000 (
#3050000
1x
1J"
1R"
1z"
14#
1<#
1l#
0f#
1+
0,
1""
1*"
1:"
1<"
1T"
1d"
1|"
1&#
1F#
#3100000
0#
1G"
1_"
1o"
1)#
11#
1Q#
1w
1I"
1Q"
1y"
13#
1;#
1k#
0j#
0"
1!"
1)"
b10000011001000011010111000000000 !
b10000011001000011010111000000000 /
19"
1@"
1X"
1h"
1"#
1*#
b1000110010100100000000000000 0
1J#
#3150000
0.
0I"
1E"
1a"
1q"
1+#
03#
1/#
b10010010101101010010111000000000 !
b10010010101101010010111000000000 /
1S#
#3200000
1O"
19#
1H"
b1001110010101100000000000000 0
12#
#3250000
0Q"
1M"
b10010000101101000010111000000000 !
b10010000101101000010111000000000 /
0;#
17#
#3300000
1W"
1A#
1P"
b1011110010111100000000000000 0
1:#
#3350000
1Y"
b10010100101101100010111000000000 !
b10010100101101100010111000000000 /
1C#
#4000000
1<
1L
1\
1d
1l
0t
0>"
0F"
0N"
0V"
0f"
0v"
0~"
0(#
00#
08#
0H#
1p#
11
19
1i
0y
1+"
0;"
0S"
1["
1k"
1s"
1-#
15#
1=#
1M#
1U#
1]#
b111010101 %
b111010101 *
b11111111111111000011100100000110 $
b11111111111111000011100100000110 (
#4050000
1P
1`
1h
0x
0J"
0R"
1j"
0d"
1$#
0|"
1,#
0&#
1L#
0F#
1s#
18
1:
1j
0""
12"
0<"
0T"
1b"
1r"
1D#
1T#
1\#
1d#
#4100000
0o"
0)#
01#
0Q#
1E
1u
0G"
0_"
1O
1_
1g
0w
1I"
0E"
1Q"
0M"
1i"
0h"
1##
0"#
0+#
1'#
0*#
1K#
0J#
1r#
17
1>
1n
0!"
11"
0@"
b11000000011000000100000100 0
0X"
0a"
1]"
0q"
1m"
0C#
1?#
0S#
1O#
1[#
b11101000011010111011100011010011 !
b11101000011010111011100011010011 /
1c#
#4150000
0O"
0W"
11#
1g"
1w"
1I#
1Y#
1q"
0m"
1+#
0'#
13#
0/#
1S#
0O#
1G
1w
0I"
b11111001111111110011101011011011 !
b11111001111111110011101011011011 /
1a"
0]"
0H"
0P"
1*#
1`"
1p"
1B#
b10111100101000000000100000100 0
1R#
#4200000
0w"
01#
09#
0Y#
0g"
0Q"
0Y"
03#
1/#
0i"
1e"
0y"
1u"
0K#
1G#
b11010000110101000011101011011011 !
b11010000110101000011101011011011 /
0[#
1W#
0p"
0*#
02#
0R#
b110000000000000000100000100 0
0`"
#4250000
19#
1o"
1!#
1Q#
1a#
1y"
0u"
13#
0/#
1;#
07#
1[#
0W#
b11110011111111000011101011011011 !
b11110011111111000011101011011011 /
1i"
0e"
12#
1h"
1x"
1J#
b101111001010000000000100000100 0
1Z#
#4300000
0!#
09#
0A#
0a#
0o"
0;#
17#
0q"
1m"
0##
1}"
0S#
1O#
b10100001101011000011101011011011 !
b10100001101011000011101011011011 /
0c#
1_#
0x"
02#
0:#
0Z#
b1100000000000000000100000100 0
0h"
#4350000
1A#
1w"
1)#
1Y#
1i#
1##
0}"
1;#
07#
1C#
0?#
1c#
0_#
b11100111111111000011101011011011 !
b11100111111111000011101011011011 /
1q"
0m"
1:#
1p"
1"#
1R#
b1011110010100000000000100000100 0
1b#
#4400000
0)#
0A#
0I#
0i#
0w"
0C#
1?#
0y"
1u"
0+#
1'#
0[#
1W#
b1000011010111000011101011011011 !
b1000011010111000011101011011011 /
0k#
1g#
0"#
0:#
0B#
0b#
b11000000000000000000100000100 0
0p"
#4450000
1I#
1!#
11#
1a#
1#
1.
1+#
0'#
1C#
0?#
1K#
0G#
1k#
0g#
b11001111111111000011101011011011 !
b11001111111111000011101011011011 /
1y"
0u"
1B#
1x"
1*#
1Z#
b10111100101000000000000100000100 0
1j#
#4500000
01#
0I#
0Q#
0#
0!#
0.
0K#
1G#
0##
1}"
03#
1/#
b10000110101111000011101011011011 !
b10000110101111000011101011011011 /
0c#
1_#
0*#
0B#
0J#
0j#
b110000000000000000000100000100 0
0x"
#4550000
1Q#
1)#
19#
1i#
13#
0/#
1K#
0G#
1S#
0O#
b10011111111111000011101011011011 !
b10011111111111000011101011011011 /
1##
0}"
1J#
1"#
12#
b1111001010000000000000100000100 0
1b#
#4600000
09#
0Q#
0Y#
0)#
0S#
1O#
0+#
1'#
0;#
17#
b1101011111000011101011011011 !
b1101011111000011101011011011 /
0k#
1g#
02#
0J#
0R#
b1100000000000000000000100000100 0
0"#
#4650000
1Y#
11#
1A#
1#
1.
1;#
07#
1S#
0O#
1[#
0W#
b111111111111000011101011011011 !
b111111111111000011101011011011 /
1+#
0'#
1R#
1*#
1:#
b11110010100000000000000100000100 0
1j#
#4700000
0A#
0Y#
0a#
01#
0[#
1W#
03#
1/#
b11010111111000011101011011011 !
b11010111111000011101011011011 /
0C#
1?#
0:#
0R#
0Z#
b11000000000000000000000100000100 0
0*#
#4750000
1a#
19#
1I#
1C#
0?#
1[#
0W#
1c#
0_#
b1111111111111000011101011011011 !
b1111111111111000011101011011011 /
13#
0/#
1Z#
12#
b11100101000000000000000100000100 0
1B#
#4800000
0I#
0a#
0i#
09#
0c#
1_#
0;#
17#
b110101111111000011101011011011 !
b110101111111000011101011011011 /
0K#
1G#
0B#
0Z#
0b#
b10000000000000000000000100000100 0
02#
#4850000
1i#
1A#
1Q#
1K#
0G#
1c#
0_#
1k#
0g#
b11111111111111000011101011011011 !
b11111111111111000011101011011011 /
1;#
07#
1b#
1:#
b11001010000000000000000100000100 0
1J#
#4900000
0Q#
0i#
0#
0A#
0.
0k#
1g#
0C#
1?#
b1101011111111000011101011011011 !
b1101011111111000011101011011011 /
0S#
1O#
0J#
0b#
0j#
b100000100 0
0:#
#4950000
1#
1I#
1Y#
1.
1S#
0O#
1k#
0g#
b11111111111111000011101011011011 !
b11111111111111000011101011011011 /
1C#
0?#
1j#
1B#
b10010100000000000000000100000100 0
1R#
#5000000
0Y#
0#
0I#
0<
0L
0\
0d
0l
1|
1&"
16"
1>"
1V"
1f"
1~"
1(#
1H#
1h#
0p#
01
09
0i
1q
0#"
0+"
03"
1;"
1C"
1K"
1S"
0["
0k"
0=#
0M#
0U#
0]#
0e#
0.
0K#
1G#
b11010111111111000011101011011011 !
b11010111111111000011101011011011 /
0[#
1W#
0R#
0j#
b100000100 0
0B#
b10001000110010100110110000000000 %
b10001000110010100110110000000000 *
b1011111010111100001000000000 $
b1011111010111100001000000000 (
#5050000
1Q#
1a#
1[#
0W#
b11111111111111000011101011011011 !
b11111111111111000011101011011011 /
1K#
0G#
0P
0`
0h
1""
0j"
1d"
0$#
1|"
0,#
1&#
0L#
1F#
0s#
0+
08
0:
0j
1x
02"
1<"
1J"
1R"
1T"
0b"
0r"
0D#
0T#
0\#
0d#
1)
1J#
b101000000000000000000100000100 0
1Z#
#5100000
0a#
1o"
1)#
11#
0E
0u
1G"
1_"
0Z#
0O
0_
0g
1!"
0i"
1h"
0##
1"#
0+#
1*#
0K#
0r#
07
0>
0n
0w
1s
01"
1@"
1I"
1Q"
b1000110010100100000000000000 0
1X"
0a"
0q"
0C#
b11010011001000011010110000001000 !
b11010011001000011010110000001000 /
0[#
#5150000
1}
0c#
1q"
1+#
03#
1/#
0G
1w
0s
0I"
1E"
b10010010101101010010111000000000 !
b10010010101101010010111000000000 /
1a"
b1000110010100100001000000000 0
1v
#5200000
19#
0}
1O"
b10010010101101010010101000000000 !
b10010010101101010010101000000000 /
0!"
1{
12#
0v
b1001110010101100000000000000 0
1H"
#5250000
1'"
0;#
17#
1!"
0{
b10010000101101000010111000000000 !
b10010000101101000010111000000000 /
0Q"
1M"
b1001110010101100010000000000 0
1~
#5300000
1A#
0'"
1W"
b10010000101101000010011000000000 !
b10010000101101000010011000000000 /
0)"
1%"
1:#
0~
b1011110010111100000000000000 0
1P"
#5350000
1/"
1C#
1)"
0%"
b10010100101101100010111000000000 !
b10010100101101100010111000000000 /
1Y"
b1011110010111100100000000000 0
1("
#5400000
0/"
b10010100101101100011111000000000 !
b10010100101101100011111000000000 /
11"
b1011110010111100000000000000 0
0("
