adder.v
// Adder circuit
`define AND2 and #30
`define OR2 or  #30
`define XOR2 xor  #30
`define NOT not #10
`define OR32 or #330
`define AND3 and  #40

module structuralFullAdder
(
    output sum,
    output carryout,
    input a,
    input b,
    input carryin

);
    wire xor0, and0, and1;
    // Single bit adder with carryin / carryout
    `XOR2 xor0gate(xor0,a,b);
    `AND2 and0gate(and0,a,b);
    `XOR2 sumgate(sum,xor0,carryin);
    `AND2 and1gate(and1,xor0,carryin);
    `OR2 orgate(carryout,and0,and1);
endmodule

module FullAdder32bit  //TODO: should change adder name to 32bit

(
  output[31:0] sum,  // 2's complement sum of a and b
  output carryout,  // Carry out of the summation of a and b
  output overflow,  // True if the calculation resulted in an overflow
  output zeros,
  input[31:0] a,     // First operand in 2's complement format
  input[31:0] b,      // Second operand in 2's complement format
  input carryin       //subtractor option
);
    // Your Code Here
    wire[31:0] carryout0;

    genvar i;
    generate
      structuralFullAdder _adder (sum[0], carryout0[0], a[0], b[0], carryin);
      for (i = 1; i < 32; i = i+1)
        begin:genblock
          structuralFullAdder _adder (sum[i],carryout0[i], a[i], b[i],carryout0[i-1]);
        end
    endgenerate
    assign carryout = carryout0[31];
    wire negand, posand, a3inv, b3inv, s3inv,one;
    //wire[31:0] sInv;
    `NOT a3inv(a3inv, a[31]);
    `NOT b3inv(b3inv, b[31]);
    `NOT s3inv(s3inv, sum[31]);
    `AND3 posand(posand, a3inv, b3inv, carryout0[30]);
    `AND3 negand(negand, a[31], b[31], s3inv);
    `OR2 overflowgate(overflow, posand, negand);
    `OR32 zeroGate(one, sum[0],sum[1],sum[2],sum[3],sum[4],sum[5],sum[6],sum[7],sum[8],sum[9],sum[10],sum[11],sum[12],sum[13],sum[14],sum[15],sum[16],sum[17],sum[18],sum[19],sum[20],sum[21],sum[22],sum[23],sum[24],sum[25],sum[26],sum[27],sum[28],sum[29],sum[30],sum[31]);
    `NOT one2zero(zeros,one);


endmodule

subtractor.v
// include and macros for timing
`include "adder.v"
`define NOT not #10

module Subtractor32bit
(
  output[31:0] diff,  // 2's complement difference of a and b
  output carryout,    // Carry out of the summation of a and b
  output overflow,    // True if the calculation resulted in an overflow
  output zeros,
  input[31:0] a,      // First operand in 2's complement format
  input[31:0] b,      // Second operand in 2's complement format
  input carryin       //subtractor option
);
    // Your Code Here
    wire[31:0] invertedB;

    genvar i;
    generate
      for (i = 0; i < 32; i = i+1)
        begin:genblock
	  `NOT _invertBGate(invertedB[i], b[i]);
        end
    endgenerate

    FullAdder32bit fulladder (diff, carryout, overflow, zeros, a, invertedB, carryin);
endmodule

SLT.v
// include and macros for timing
`include "subtractor.v"
`define XOR xor #30

module SLT
(
  output[31:0] res,  // less than
  input[31:0] a,     // First operand in 2's complement format
  input[31:0] b,     // Second operand in 2's complement format
  input carryin      //subtractor option
);
    // Your Code Here
    wire carryout;   // Carry out of the summation of a and b
    wire overflow;   // True if the calculation resulted in an overflow
    wire zeros;
    wire [31:0] diff;
    Subtractor32bit fullSubtractor (diff, carryout, overflow, zeros, a, b, carryin);
    wire lessThan;
    `XOR handleOverflowGate(lessThan, diff[31], overflow);

    assign res[31:1] = 0;
    assign res[0] = lessThan;

endmodule

SLT.t.v
// Adder testbench
`timescale 1 ns / 1 ps
`include "SLT.v"

module testSLT();
    reg [31:0] a, b;
    reg carryin;
    wire [31:0] result;
    reg overflow, carryout, zero;

    SLT SLT32 (result, a, b,1);


    initial begin
    overflow = 0; carryout = 0; zero = 0;
    $dumpfile("slt.vcd");
    $dumpvars;
        $display("result                           overflow carryout zero | Eresult                          Eoverflow Ecarryout Ezero");
        a = 32'b01111111111111111111111111111111; b = 32'b00000000000000000000000000000001; #2000
        if((result !== 32'b00000000000000000000000000000000) || (overflow !== 0) || (carryout !== 0) || (zero !== 0)) begin
          $display("%b                                %b        %b        %b    | 00000000000000000000000000000000 0         0         0",result,overflow,carryout,zero);
        end
        a = 32'b00000000000000000000000000000001; b = 32'b01111111111111111111111111111111; #2000
        if((result !== 32'b00000000000000000000000000000001) || (overflow !== 0) || (carryout !== 0) || (zero !== 0)) begin
          $display("%b                                %b        %b        %b    | 00000000000000000000000000000001 0         0         0",result,overflow,carryout,zero);
        end
        a = 32'b10000000000000000000000000000000; b = 32'b10000000000000000000000000000000; #2000
        if((result !== 32'b00000000000000000000000000000000) || (overflow !== 0) || (carryout !== 0) || (zero !== 0)) begin
          $display("%b                                %b        %b        %b    | 00000000000000000000000000000000 0         0         0",result,overflow,carryout,zero);
        end
        a = 32'b10001000110010100110110000000000; b = 32'b00001011111010111100001000000000; #2000
        if((result !== 32'b00000000000000000000000000000001) || (overflow !== 0) || (carryout !== 0) || (zero !== 0)) begin
          $display("%b                                %b        %b        %b    | 00000000000000000000000000000001 0         0         0",result,overflow,carryout,zero);
        end
        a = 32'b11111111111111000011100100000110; b = 32'b00000000000000000000000111010101; #2000
        if((result !== 32'b00000000000000000000000000000001) || (overflow !== 0) || (carryout !== 0) || (zero !== 0)) begin
          $display("%b                                %b        %b        %b    | 00000000000000000000000000000001 0         0         0",result,overflow,carryout,zero);
        end
        a = 32'b00001011111010111100001000000000; b = 32'b10001000110010100110110000000000; #2000
        if((result !== 32'b00000000000000000000000000000000) || (overflow !== 0) || (carryout !== 0) || (zero !== 0)) begin
          $display("%b                                %b        %b        %b    | 00000000000000000000000000000000 0         0         0",result,overflow,carryout,zero);
        end
        a = 32'b00000000010110010101011000100100; b = 32'b11111111111111111111110100010010; #2000
        if((result !== 32'b00000000000000000000000000000000) || (overflow !== 0) || (carryout !== 0) || (zero !== 0)) begin
          $display(" %b                                %b        %b        %b    | 00000000000000000000000000000000 0         0         0",result,overflow,carryout,zero);
        end
        a = 32'b00000000000000000000001111101000; b = 32'b00000000000000000000001111101000; #2000
        if((result !== 32'b00000000000000000000000000000000) || (overflow !== 0) || (carryout !== 0) || (zero !== 0)) begin
          $display("%b                                %b        %b        %b    | 00000000000000000000000000000000 0         0         0",result,overflow,carryout,zero);
        end
        a = 32'b11111111111111111111110000011000; b = 32'b11111111111111111111110000011000; #2000
        if((result !== 32'b00000000000000000000000000000000) || (overflow !== 0) || (carryout !== 0) || (zero !== 0)) begin
          $display("%b                                %b        %b        %b    | 00000000000000000000000000000000 0         0         0",result,overflow,carryout,zero);
        end
        a = 32'b00000000000000000000000000000000; b = 32'b00000000000000000000000000000000; #2000
        if((result !== 32'b00000000000000000000000000000000) || (overflow !== 0) || (carryout !== 0) || (zero !== 0)) begin
          $display("%b                                %b        %b        %b    | 00000000000000000000000000000000 0         0         0",result,overflow,carryout,zero);
        end
        a = 32'b00000000000001100001101010000000; b = 32'b11111111111110011110010110000000; #2000
        if((result !== 32'b00000000000000000000000000000000) || (overflow !== 0) || (carryout !== 0) || (zero !== 0)) begin
          $display("%b                                %b        %b        %b    | 00000000000000000000000000000000 0         0         0",result,overflow,carryout,zero);
        end
    end
endmodule

slt.vcd
$date
	Thu Oct  4 15:12:32 2018
$end
$version
	Icarus Verilog
$end
$timescale
	1ps
$end
$scope module testSLT $end
$var wire 32 ! result [31:0] $end
$var reg 32 " a [31:0] $end
$var reg 32 # b [31:0] $end
$var reg 1 $ carryout $end
$var reg 1 % overflow $end
$var reg 1 & zero $end
$scope module SLT32 $end
$var wire 32 ' a [31:0] $end
$var wire 32 ( b [31:0] $end
$var wire 1 ) carryin $end
$var wire 1 * lessThan $end
$var wire 1 + zeros $end
$var wire 32 , res [31:0] $end
$var wire 1 - overflow $end
$var wire 32 . diff [31:0] $end
$var wire 1 / carryout $end
$scope module fullSubtractor $end
$var wire 32 0 a [31:0] $end
$var wire 32 1 b [31:0] $end
$var wire 1 ) carryin $end
$var wire 1 + zeros $end
$var wire 1 - overflow $end
$var wire 32 2 invertedB [31:0] $end
$var wire 32 3 diff [31:0] $end
$var wire 1 / carryout $end
$scope begin genblock[0] $end
$upscope $end
$scope begin genblock[1] $end
$upscope $end
$scope begin genblock[2] $end
$upscope $end
$scope begin genblock[3] $end
$upscope $end
$scope begin genblock[4] $end
$upscope $end
$scope begin genblock[5] $end
$upscope $end
$scope begin genblock[6] $end
$upscope $end
$scope begin genblock[7] $end
$upscope $end
$scope begin genblock[8] $end
$upscope $end
$scope begin genblock[9] $end
$upscope $end
$scope begin genblock[10] $end
$upscope $end
$scope begin genblock[11] $end
$upscope $end
$scope begin genblock[12] $end
$upscope $end
$scope begin genblock[13] $end
$upscope $end
$scope begin genblock[14] $end
$upscope $end
$scope begin genblock[15] $end
$upscope $end
$scope begin genblock[16] $end
$upscope $end
$scope begin genblock[17] $end
$upscope $end
$scope begin genblock[18] $end
$upscope $end
$scope begin genblock[19] $end
$upscope $end
$scope begin genblock[20] $end
$upscope $end
$scope begin genblock[21] $end
$upscope $end
$scope begin genblock[22] $end
$upscope $end
$scope begin genblock[23] $end
$upscope $end
$scope begin genblock[24] $end
$upscope $end
$scope begin genblock[25] $end
$upscope $end
$scope begin genblock[26] $end
$upscope $end
$scope begin genblock[27] $end
$upscope $end
$scope begin genblock[28] $end
$upscope $end
$scope begin genblock[29] $end
$upscope $end
$scope begin genblock[30] $end
$upscope $end
$scope begin genblock[31] $end
$upscope $end
$scope module fulladder $end
$var wire 32 4 a [31:0] $end
$var wire 1 5 a3inv $end
$var wire 32 6 b [31:0] $end
$var wire 1 7 b3inv $end
$var wire 1 ) carryin $end
$var wire 1 8 negand $end
$var wire 1 9 one $end
$var wire 1 - overflow $end
$var wire 1 : posand $end
$var wire 1 ; s3inv $end
$var wire 1 + zeros $end
$var wire 32 < sum [31:0] $end
$var wire 32 = carryout0 [31:0] $end
$var wire 1 / carryout $end
$scope begin genblock[1] $end
$scope module _adder $end
$var wire 1 > a $end
$var wire 1 ? and0 $end
$var wire 1 @ and1 $end
$var wire 1 A b $end
$var wire 1 B carryin $end
$var wire 1 C carryout $end
$var wire 1 D sum $end
$var wire 1 E xor0 $end
$upscope $end
$upscope $end
$scope begin genblock[2] $end
$scope module _adder $end
$var wire 1 F a $end
$var wire 1 G and0 $end
$var wire 1 H and1 $end
$var wire 1 I b $end
$var wire 1 J carryin $end
$var wire 1 K carryout $end
$var wire 1 L sum $end
$var wire 1 M xor0 $end
$upscope $end
$upscope $end
$scope begin genblock[3] $end
$scope module _adder $end
$var wire 1 N a $end
$var wire 1 O and0 $end
$var wire 1 P and1 $end
$var wire 1 Q b $end
$var wire 1 R carryin $end
$var wire 1 S carryout $end
$var wire 1 T sum $end
$var wire 1 U xor0 $end
$upscope $end
$upscope $end
$scope begin genblock[4] $end
$scope module _adder $end
$var wire 1 V a $end
$var wire 1 W and0 $end
$var wire 1 X and1 $end
$var wire 1 Y b $end
$var wire 1 Z carryin $end
$var wire 1 [ carryout $end
$var wire 1 \ sum $end
$var wire 1 ] xor0 $end
$upscope $end
$upscope $end
$scope begin genblock[5] $end
$scope module _adder $end
$var wire 1 ^ a $end
$var wire 1 _ and0 $end
$var wire 1 ` and1 $end
$var wire 1 a b $end
$var wire 1 b carryin $end
$var wire 1 c carryout $end
$var wire 1 d sum $end
$var wire 1 e xor0 $end
$upscope $end
$upscope $end
$scope begin genblock[6] $end
$scope module _adder $end
$var wire 1 f a $end
$var wire 1 g and0 $end
$var wire 1 h and1 $end
$var wire 1 i b $end
$var wire 1 j carryin $end
$var wire 1 k carryout $end
$var wire 1 l sum $end
$var wire 1 m xor0 $end
$upscope $end
$upscope $end
$scope begin genblock[7] $end
$scope module _adder $end
$var wire 1 n a $end
$var wire 1 o and0 $end
$var wire 1 p and1 $end
$var wire 1 q b $end
$var wire 1 r carryin $end
$var wire 1 s carryout $end
$var wire 1 t sum $end
$var wire 1 u xor0 $end
$upscope $end
$upscope $end
$scope begin genblock[8] $end
$scope module _adder $end
$var wire 1 v a $end
$var wire 1 w and0 $end
$var wire 1 x and1 $end
$var wire 1 y b $end
$var wire 1 z carryin $end
$var wire 1 { carryout $end
$var wire 1 | sum $end
$var wire 1 } xor0 $end
$upscope $end
$upscope $end
$scope begin genblock[9] $end
$scope module _adder $end
$var wire 1 ~ a $end
$var wire 1 !" and0 $end
$var wire 1 "" and1 $end
$var wire 1 #" b $end
$var wire 1 $" carryin $end
$var wire 1 %" carryout $end
$var wire 1 &" sum $end
$var wire 1 '" xor0 $end
$upscope $end
$upscope $end
$scope begin genblock[10] $end
$scope module _adder $end
$var wire 1 (" a $end
$var wire 1 )" and0 $end
$var wire 1 *" and1 $end
$var wire 1 +" b $end
$var wire 1 ," carryin $end
$var wire 1 -" carryout $end
$var wire 1 ." sum $end
$var wire 1 /" xor0 $end
$upscope $end
$upscope $end
$scope begin genblock[11] $end
$scope module _adder $end
$var wire 1 0" a $end
$var wire 1 1" and0 $end
$var wire 1 2" and1 $end
$var wire 1 3" b $end
$var wire 1 4" carryin $end
$var wire 1 5" carryout $end
$var wire 1 6" sum $end
$var wire 1 7" xor0 $end
$upscope $end
$upscope $end
$scope begin genblock[12] $end
$scope module _adder $end
$var wire 1 8" a $end
$var wire 1 9" and0 $end
$var wire 1 :" and1 $end
$var wire 1 ;" b $end
$var wire 1 <" carryin $end
$var wire 1 =" carryout $end
$var wire 1 >" sum $end
$var wire 1 ?" xor0 $end
$upscope $end
$upscope $end
$scope begin genblock[13] $end
$scope module _adder $end
$var wire 1 @" a $end
$var wire 1 A" and0 $end
$var wire 1 B" and1 $end
$var wire 1 C" b $end
$var wire 1 D" carryin $end
$var wire 1 E" carryout $end
$var wire 1 F" sum $end
$var wire 1 G" xor0 $end
$upscope $end
$upscope $end
$scope begin genblock[14] $end
$scope module _adder $end
$var wire 1 H" a $end
$var wire 1 I" and0 $end
$var wire 1 J" and1 $end
$var wire 1 K" b $end
$var wire 1 L" carryin $end
$var wire 1 M" carryout $end
$var wire 1 N" sum $end
$var wire 1 O" xor0 $end
$upscope $end
$upscope $end
$scope begin genblock[15] $end
$scope module _adder $end
$var wire 1 P" a $end
$var wire 1 Q" and0 $end
$var wire 1 R" and1 $end
$var wire 1 S" b $end
$var wire 1 T" carryin $end
$var wire 1 U" carryout $end
$var wire 1 V" sum $end
$var wire 1 W" xor0 $end
$upscope $end
$upscope $end
$scope begin genblock[16] $end
$scope module _adder $end
$var wire 1 X" a $end
$var wire 1 Y" and0 $end
$var wire 1 Z" and1 $end
$var wire 1 [" b $end
$var wire 1 \" carryin $end
$var wire 1 ]" carryout $end
$var wire 1 ^" sum $end
$var wire 1 _" xor0 $end
$upscope $end
$upscope $end
$scope begin genblock[17] $end
$scope module _adder $end
$var wire 1 `" a $end
$var wire 1 a" and0 $end
$var wire 1 b" and1 $end
$var wire 1 c" b $end
$var wire 1 d" carryin $end
$var wire 1 e" carryout $end
$var wire 1 f" sum $end
$var wire 1 g" xor0 $end
$upscope $end
$upscope $end
$scope begin genblock[18] $end
$scope module _adder $end
$var wire 1 h" a $end
$var wire 1 i" and0 $end
$var wire 1 j" and1 $end
$var wire 1 k" b $end
$var wire 1 l" carryin $end
$var wire 1 m" carryout $end
$var wire 1 n" sum $end
$var wire 1 o" xor0 $end
$upscope $end
$upscope $end
$scope begin genblock[19] $end
$scope module _adder $end
$var wire 1 p" a $end
$var wire 1 q" and0 $end
$var wire 1 r" and1 $end
$var wire 1 s" b $end
$var wire 1 t" carryin $end
$var wire 1 u" carryout $end
$var wire 1 v" sum $end
$var wire 1 w" xor0 $end
$upscope $end
$upscope $end
$scope begin genblock[20] $end
$scope module _adder $end
$var wire 1 x" a $end
$var wire 1 y" and0 $end
$var wire 1 z" and1 $end
$var wire 1 {" b $end
$var wire 1 |" carryin $end
$var wire 1 }" carryout $end
$var wire 1 ~" sum $end
$var wire 1 !# xor0 $end
$upscope $end
$upscope $end
$scope begin genblock[21] $end
$scope module _adder $end
$var wire 1 "# a $end
$var wire 1 ## and0 $end
$var wire 1 $# and1 $end
$var wire 1 %# b $end
$var wire 1 &# carryin $end
$var wire 1 '# carryout $end
$var wire 1 (# sum $end
$var wire 1 )# xor0 $end
$upscope $end
$upscope $end
$scope begin genblock[22] $end
$scope module _adder $end
$var wire 1 *# a $end
$var wire 1 +# and0 $end
$var wire 1 ,# and1 $end
$var wire 1 -# b $end
$var wire 1 .# carryin $end
$var wire 1 /# carryout $end
$var wire 1 0# sum $end
$var wire 1 1# xor0 $end
$upscope $end
$upscope $end
$scope begin genblock[23] $end
$scope module _adder $end
$var wire 1 2# a $end
$var wire 1 3# and0 $end
$var wire 1 4# and1 $end
$var wire 1 5# b $end
$var wire 1 6# carryin $end
$var wire 1 7# carryout $end
$var wire 1 8# sum $end
$var wire 1 9# xor0 $end
$upscope $end
$upscope $end
$scope begin genblock[24] $end
$scope module _adder $end
$var wire 1 :# a $end
$var wire 1 ;# and0 $end
$var wire 1 <# and1 $end
$var wire 1 =# b $end
$var wire 1 ># carryin $end
$var wire 1 ?# carryout $end
$var wire 1 @# sum $end
$var wire 1 A# xor0 $end
$upscope $end
$upscope $end
$scope begin genblock[25] $end
$scope module _adder $end
$var wire 1 B# a $end
$var wire 1 C# and0 $end
$var wire 1 D# and1 $end
$var wire 1 E# b $end
$var wire 1 F# carryin $end
$var wire 1 G# carryout $end
$var wire 1 H# sum $end
$var wire 1 I# xor0 $end
$upscope $end
$upscope $end
$scope begin genblock[26] $end
$scope module _adder $end
$var wire 1 J# a $end
$var wire 1 K# and0 $end
$var wire 1 L# and1 $end
$var wire 1 M# b $end
$var wire 1 N# carryin $end
$var wire 1 O# carryout $end
$var wire 1 P# sum $end
$var wire 1 Q# xor0 $end
$upscope $end
$upscope $end
$scope begin genblock[27] $end
$scope module _adder $end
$var wire 1 R# a $end
$var wire 1 S# and0 $end
$var wire 1 T# and1 $end
$var wire 1 U# b $end
$var wire 1 V# carryin $end
$var wire 1 W# carryout $end
$var wire 1 X# sum $end
$var wire 1 Y# xor0 $end
$upscope $end
$upscope $end
$scope begin genblock[28] $end
$scope module _adder $end
$var wire 1 Z# a $end
$var wire 1 [# and0 $end
$var wire 1 \# and1 $end
$var wire 1 ]# b $end
$var wire 1 ^# carryin $end
$var wire 1 _# carryout $end
$var wire 1 `# sum $end
$var wire 1 a# xor0 $end
$upscope $end
$upscope $end
$scope begin genblock[29] $end
$scope module _adder $end
$var wire 1 b# a $end
$var wire 1 c# and0 $end
$var wire 1 d# and1 $end
$var wire 1 e# b $end
$var wire 1 f# carryin $end
$var wire 1 g# carryout $end
$var wire 1 h# sum $end
$var wire 1 i# xor0 $end
$upscope $end
$upscope $end
$scope begin genblock[30] $end
$scope module _adder $end
$var wire 1 j# a $end
$var wire 1 k# and0 $end
$var wire 1 l# and1 $end
$var wire 1 m# b $end
$var wire 1 n# carryin $end
$var wire 1 o# carryout $end
$var wire 1 p# sum $end
$var wire 1 q# xor0 $end
$upscope $end
$upscope $end
$scope begin genblock[31] $end
$scope module _adder $end
$var wire 1 r# a $end
$var wire 1 s# and0 $end
$var wire 1 t# and1 $end
$var wire 1 u# b $end
$var wire 1 v# carryin $end
$var wire 1 w# carryout $end
$var wire 1 x# sum $end
$var wire 1 y# xor0 $end
$upscope $end
$upscope $end
$scope module _adder $end
$var wire 1 z# a $end
$var wire 1 {# and0 $end
$var wire 1 |# and1 $end
$var wire 1 }# b $end
$var wire 1 ) carryin $end
$var wire 1 ~# carryout $end
$var wire 1 !$ sum $end
$var wire 1 "$ xor0 $end
$upscope $end
$upscope $end
$upscope $end
$upscope $end
$upscope $end
$enddefinitions $end
#0
$dumpvars
x"$
x!$
x~#
x}#
x|#
x{#
1z#
xy#
xx#
xw#
xv#
xu#
xt#
xs#
0r#
xq#
xp#
xo#
xn#
xm#
xl#
xk#
1j#
xi#
xh#
xg#
xf#
xe#
xd#
xc#
1b#
xa#
x`#
x_#
x^#
x]#
x\#
x[#
1Z#
xY#
xX#
xW#
xV#
xU#
xT#
xS#
1R#
xQ#
xP#
xO#
xN#
xM#
xL#
xK#
1J#
xI#
xH#
xG#
xF#
xE#
xD#
xC#
1B#
xA#
x@#
x?#
x>#
x=#
x<#
x;#
1:#
x9#
x8#
x7#
x6#
x5#
x4#
x3#
12#
x1#
x0#
x/#
x.#
x-#
x,#
x+#
1*#
x)#
x(#
x'#
x&#
x%#
x$#
x##
1"#
x!#
x~"
x}"
x|"
x{"
xz"
xy"
1x"
xw"
xv"
xu"
xt"
xs"
xr"
xq"
1p"
xo"
xn"
xm"
xl"
xk"
xj"
xi"
1h"
xg"
xf"
xe"
xd"
xc"
xb"
xa"
1`"
x_"
x^"
x]"
x\"
x["
xZ"
xY"
1X"
xW"
xV"
xU"
xT"
xS"
xR"
xQ"
1P"
xO"
xN"
xM"
xL"
xK"
xJ"
xI"
1H"
xG"
xF"
xE"
xD"
xC"
xB"
xA"
1@"
x?"
x>"
x="
x<"
x;"
x:"
x9"
18"
x7"
x6"
x5"
x4"
x3"
x2"
x1"
10"
x/"
x."
x-"
x,"
x+"
x*"
x)"
1("
x'"
x&"
x%"
x$"
x#"
x""
x!"
1~
x}
x|
x{
xz
xy
xx
xw
1v
xu
xt
xs
xr
xq
xp
xo
1n
xm
xl
xk
xj
xi
xh
xg
1f
xe
xd
xc
xb
xa
x`
x_
1^
x]
x\
x[
xZ
xY
xX
xW
1V
xU
xT
xS
xR
xQ
xP
xO
1N
xM
xL
xK
xJ
xI
xH
xG
1F
xE
xD
xC
xB
xA
x@
x?
1>
bx =
bx <
x;
x:
x9
x8
x7
bx 6
x5
b1111111111111111111111111111111 4
bx 3
bx 2
b1 1
b1111111111111111111111111111111 0
x/
bx .
x-
b0x ,
x+
x*
1)
b1 (
b1111111111111111111111111111111 '
0&
0%
0$
b1 #
b1111111111111111111111111111111 "
b0x !
$end
#10000
0}#
1A
1I
1Q
1Y
1a
1i
1q
1y
1#"
1+"
13"
1;"
1C"
1K"
1S"
1["
1c"
1k"
1s"
1{"
1%#
1-#
15#
1=#
1E#
1M#
1U#
1]#
1e#
1m#
1u#
b11111111111111111111111111111110 2
b11111111111111111111111111111110 6
15
#20000
07
#30000
0s#
#40000
1"$
0{#
0E
1?
0M
1G
0U
1O
0]
1W
0e
1_
0m
1g
0u
1o
0}
1w
0'"
1!"
0/"
1)"
07"
11"
0?"
19"
0G"
1A"
0O"
1I"
0W"
1Q"
0_"
1Y"
0g"
1a"
0o"
1i"
0w"
1q"
0!#
1y"
0)#
1##
01#
1+#
09#
13#
0A#
1;#
0I#
1C#
0Q#
1K#
0Y#
1S#
0a#
1[#
0i#
1c#
0q#
1k#
1y#
08
#60000
0:
#70000
1J
1R
1Z
1b
1j
1r
1z
1$"
1,"
14"
1<"
1D"
1L"
1T"
1\"
1d"
1l"
1t"
1|"
1&#
1.#
16#
1>#
1F#
1N#
1V#
1^#
1f#
1n#
1v#
bx0 .
bx0 3
bx0 <
0!$
1|#
0@
1C
0H
1K
0P
1S
0X
1[
0`
1c
0h
1k
0p
1s
0x
1{
0""
1%"
0*"
1-"
02"
15"
0:"
1="
0B"
1E"
0J"
1M"
0R"
1U"
0Z"
1]"
0b"
1e"
0j"
1m"
0r"
1u"
0z"
1}"
0$#
1'#
0,#
1/#
04#
17#
0<#
1?#
0D#
1G#
0L#
1O#
0T#
1W#
0\#
1_#
0d#
1g#
0l#
bx111111111111111111111111111111x =
1o#
#90000
0-
#100000
1B
1L
1T
1\
1d
1l
1t
1|
1&"
1."
16"
1>"
1F"
1N"
1V"
1^"
1f"
1n"
1v"
1~"
1(#
10#
18#
1@#
1H#
1P#
1X#
1`#
1h#
1p#
b11111111111111111111111111111x0 .
b11111111111111111111111111111x0 3
b11111111111111111111111111111x0 <
0x#
1t#
bx1111111111111111111111111111111 =
1~#
#110000
1;
#130000
1/
b0 !
b0 ,
0*
b1111111111111111111111111111110 .
b1111111111111111111111111111110 3
b1111111111111111111111111111110 <
1D
b11111111111111111111111111111111 =
1w#
#430000
19
#440000
0+
#2000000
0>
0F
0N
0V
0^
0f
0n
0v
0~
0("
00"
08"
0@"
0H"
0P"
0X"
0`"
0h"
0p"
0x"
0"#
0*#
02#
0:#
0B#
0J#
0R#
0Z#
0b#
0j#
b1111111111111111111111111111111 #
b1111111111111111111111111111111 (
b1111111111111111111111111111111 1
b1 "
b1 '
b1 0
b1 4
#2010000
0A
0I
0Q
0Y
0a
0i
0q
0y
0#"
0+"
03"
0;"
0C"
0K"
0S"
0["
0c"
0k"
0s"
0{"
0%#
0-#
05#
0=#
0E#
0M#
0U#
0]#
0e#
0m#
b10000000000000000000000000000000 2
b10000000000000000000000000000000 6
#2030000
0?
0G
0O
0W
0_
0g
0o
0w
0!"
0)"
01"
09"
0A"
0I"
0Q"
0Y"
0a"
0i"
0q"
0y"
0##
0+#
03#
0;#
0C#
0K#
0S#
0[#
0c#
0k#
#2060000
0J
0R
0Z
0b
0j
0r
0z
0$"
0,"
04"
0<"
0D"
0L"
0T"
0\"
0d"
0l"
0t"
0|"
0&#
0.#
06#
0>#
0F#
0N#
0V#
0^#
0f#
0n#
0v#
0C
0K
0S
0[
0c
0k
0s
0{
0%"
0-"
05"
0="
0E"
0M"
0U"
0]"
0e"
0m"
0u"
0}"
0'#
0/#
07#
0?#
0G#
0O#
0W#
0_#
0g#
b10000000000000000000000000000001 =
0o#
#2090000
0L
0T
0\
0d
0l
0t
0|
0&"
0."
06"
0>"
0F"
0N"
0V"
0^"
0f"
0n"
0v"
0~"
0(#
00#
08#
0@#
0H#
0P#
0X#
0`#
0h#
0p#
b10000000000000000000000000000010 .
b10000000000000000000000000000010 3
b10000000000000000000000000000010 <
1x#
0t#
#2100000
0;
#2120000
0/
b1 !
b1 ,
1*
b1 =
0w#
#4000000
1r#
0z#
b10000000000000000000000000000000 #
b10000000000000000000000000000000 (
b10000000000000000000000000000000 1
b10000000000000000000000000000000 "
b10000000000000000000000000000000 '
b10000000000000000000000000000000 0
b10000000000000000000000000000000 4
#4010000
1}#
1A
1I
1Q
1Y
1a
1i
1q
1y
1#"
1+"
13"
1;"
1C"
1K"
1S"
1["
1c"
1k"
1s"
1{"
1%#
1-#
15#
1=#
1E#
1M#
1U#
1]#
1e#
1m#
0u#
b1111111111111111111111111111111 2
b1111111111111111111111111111111 6
05
#4020000
17
#4040000
1E
1M
1U
1]
1e
1m
1u
1}
1'"
1/"
17"
1?"
1G"
1O"
1W"
1_"
1g"
1o"
1w"
1!#
1)#
11#
19#
1A#
1I#
1Q#
1Y#
1a#
1i#
1q#
#4070000
0D
1@
1L
1T
1\
1d
1l
1t
1|
1&"
1."
16"
1>"
1F"
1N"
1V"
1^"
1f"
1n"
1v"
1~"
1(#
10#
18#
1@#
1H#
1P#
1X#
1`#
1h#
b11111111111111111111111111111100 .
b11111111111111111111111111111100 3
b11111111111111111111111111111100 <
1p#
#4100000
1J
b11 =
1C
#4130000
b11111111111111111111111111111000 .
b11111111111111111111111111111000 3
b11111111111111111111111111111000 <
0L
1H
#4160000
1R
b111 =
1K
#4190000
b11111111111111111111111111110000 .
b11111111111111111111111111110000 3
b11111111111111111111111111110000 <
0T
1P
#4220000
1Z
b1111 =
1S
#4250000
b11111111111111111111111111100000 .
b11111111111111111111111111100000 3
b11111111111111111111111111100000 <
0\
1X
#4280000
1b
b11111 =
1[
#4310000
b11111111111111111111111111000000 .
b11111111111111111111111111000000 3
b11111111111111111111111111000000 <
0d
1`
#4340000
1j
b111111 =
1c
#4370000
b11111111111111111111111110000000 .
b11111111111111111111111110000000 3
b11111111111111111111111110000000 <
0l
1h
#4400000
1r
b1111111 =
1k
#4430000
b11111111111111111111111100000000 .
b11111111111111111111111100000000 3
b11111111111111111111111100000000 <
0t
1p
#4460000
1z
b11111111 =
1s
#4490000
b11111111111111111111111000000000 .
b11111111111111111111111000000000 3
b11111111111111111111111000000000 <
0|
1x
#4520000
1$"
b111111111 =
1{
#4550000
b11111111111111111111110000000000 .
b11111111111111111111110000000000 3
b11111111111111111111110000000000 <
0&"
1""
#4580000
1,"
b1111111111 =
1%"
#4610000
b11111111111111111111100000000000 .
b11111111111111111111100000000000 3
b11111111111111111111100000000000 <
0."
1*"
#4640000
14"
b11111111111 =
1-"
#4670000
b11111111111111111111000000000000 .
b11111111111111111111000000000000 3
b11111111111111111111000000000000 <
06"
12"
#4700000
1<"
b111111111111 =
15"
#4730000
b11111111111111111110000000000000 .
b11111111111111111110000000000000 3
b11111111111111111110000000000000 <
0>"
1:"
#4760000
1D"
b1111111111111 =
1="
#4790000
b11111111111111111100000000000000 .
b11111111111111111100000000000000 3
b11111111111111111100000000000000 <
0F"
1B"
#4820000
1L"
b11111111111111 =
1E"
#4850000
b11111111111111111000000000000000 .
b11111111111111111000000000000000 3
b11111111111111111000000000000000 <
0N"
1J"
#4880000
1T"
b111111111111111 =
1M"
#4910000
b11111111111111110000000000000000 .
b11111111111111110000000000000000 3
b11111111111111110000000000000000 <
0V"
1R"
#4940000
1\"
b1111111111111111 =
1U"
#4970000
b11111111111111100000000000000000 .
b11111111111111100000000000000000 3
b11111111111111100000000000000000 <
0^"
1Z"
#5000000
1d"
b11111111111111111 =
1]"
#5030000
b11111111111111000000000000000000 .
b11111111111111000000000000000000 3
b11111111111111000000000000000000 <
0f"
1b"
#5060000
1l"
b111111111111111111 =
1e"
#5090000
b11111111111110000000000000000000 .
b11111111111110000000000000000000 3
b11111111111110000000000000000000 <
0n"
1j"
#5120000
1t"
b1111111111111111111 =
1m"
#5150000
b11111111111100000000000000000000 .
b11111111111100000000000000000000 3
b11111111111100000000000000000000 <
0v"
1r"
#5180000
1|"
b11111111111111111111 =
1u"
#5210000
b11111111111000000000000000000000 .
b11111111111000000000000000000000 3
b11111111111000000000000000000000 <
0~"
1z"
#5240000
1&#
b111111111111111111111 =
1}"
#5270000
b11111111110000000000000000000000 .
b11111111110000000000000000000000 3
b11111111110000000000000000000000 <
0(#
1$#
#5300000
1.#
b1111111111111111111111 =
1'#
